verilog_code/cpe300/lab4_code/exp2/reg4d.v
/*
    4-bit reg from Dff, structual model
*/

`timescale 1ns/1ns
`define HALF 5
`define REPS 4
`define SEED 888


module tb();
    wire [3:0] Q;
    reg [3:0] D;
    reg clrN;
    reg clk;

    integer ii;
    integer jj;
    integer seed;

    reg4d DUT (
                .q_bus(Q),
                .d_bus(D),
                .clrN(clrN),
                .clk(clk)
        );
    
    always begin
        #`HALF;
        clk = ~clk;
    end

    initial begin
        $dumpfile("wave.vcd");
        $dumpvars(0, tb);
        $write("\ntest the structural Dff, in 4-bit reg\n\n");
        clrN = 1'b1;
        clk = 1'b0;
        D = 4'b0000;
        seed = `SEED;
        $write(" clrN    D   |   Q \n");
        $write(" --------------------\n\n");

        for (ii = 0; ii < `REPS; ii = ii + 1) begin
            for (jj = 0; jj < 4; jj = jj + 1) begin
                D[jj] = $random(seed) % 2;
            end
            #(`HALF - 1);
            $write("  %1b    %4b  |  %4b      %3t ns  before edge\n",
                clrN, D, Q, $time);
            #2;
            $write("  %1b    %1b  |  %4b      %3t ns  after edge\n\n",
                clrN, D, Q, $time);
            #(`HALF - 1);
        end

        clrN = 1'b0;
        $write(" --------------------\n\n");
        for (ii = 0; ii < `REPS; ii = ii + 1) begin
            for (jj = 0; jj < 4; jj = jj + 1) begin
                D[jj] = $random(seed) % 2;
            end
            #(`HALF - 1);
            $write("  %1b    %4b  |  %4b      %3t ns  before edge\n",
                clrN, D, Q, $time);
            #2;
            $write("  %1b    %1b  |  %4b      %3t ns  after edge\n\n",
                clrN, D, Q, $time);
            #(`HALF - 1);
        end
        
        
        $write("\n\n\t\t ~ ~ ~ TEST COMPLETE ~ ~ ~\n\n");
        $finish;
    end

endmodule


////~~~~


module reg4d (
                output wire [3:0] q_bus,
                input wire [3:0] d_bus,
                input wire clrN,
                input wire clk
        );
    
    dFF_struct dff_0 (
                        .outQ(q_bus[0]),
                        .inD(d_bus[0]),
                        .clearN(clrN),
                        .clock(clk)
                );
    
    dFF_struct dff_1 (
                        .outQ(q_bus[1]),
                        .inD(d_bus[1]),
                        .clearN(clrN),
                        .clock(clk)
                );
    
    dFF_struct dff_2 (
                        .outQ(q_bus[2]),
                        .inD(d_bus[2]),
                        .clearN(clrN),
                        .clock(clk)
                );
    
    dFF_struct dff_3 (
                        .outQ(q_bus[3]),
                        .inD(d_bus[3]),
                        .clearN(clrN),
                        .clock(clk)
                );
    
endmodule


////~~~~


module dFF_struct(
                    output wire outQ,
                    input wire inD,
                    input wire clearN,
                    input wire clock
                );
    wire w_not;
    wire w_and1;
    wire w_and2;
    wire w_nor1;
    wire w_nor2;

    not(w_not, inD);
    and(w_and1, w_not, clock);
    and(w_and2, inD, clock);
    nor(w_nor1, w_and1, w_nor2);
    nor(w_nor2, w_and2, w_nor1);
    
    assign outQ = w_nor1 & clearN;
endmodule


////////~~~~~~~~END>  reg4d.v

verilog_code/cpe300/lab4_code/exp2/wave.vcd
$date
	Mon Sep 27 10:27:32 2021
$end
$version
	Icarus Verilog
$end
$timescale
	1ns
$end
$scope module tb $end
$var wire 4 ! Q [3:0] $end
$var reg 4 " D [3:0] $end
$var reg 1 # clk $end
$var reg 1 $ clrN $end
$var integer 32 % ii [31:0] $end
$var integer 32 & jj [31:0] $end
$var integer 32 ' seed [31:0] $end
$scope module DUT $end
$var wire 1 # clk $end
$var wire 1 $ clrN $end
$var wire 4 ( d_bus [3:0] $end
$var wire 4 ) q_bus [3:0] $end
$scope module dff_0 $end
$var wire 1 $ clearN $end
$var wire 1 # clock $end
$var wire 1 * inD $end
$var wire 1 + outQ $end
$var wire 1 , w_and1 $end
$var wire 1 - w_and2 $end
$var wire 1 . w_nor1 $end
$var wire 1 / w_nor2 $end
$var wire 1 0 w_not $end
$upscope $end
$scope module dff_1 $end
$var wire 1 $ clearN $end
$var wire 1 # clock $end
$var wire 1 1 inD $end
$var wire 1 2 outQ $end
$var wire 1 3 w_and1 $end
$var wire 1 4 w_and2 $end
$var wire 1 5 w_nor1 $end
$var wire 1 6 w_nor2 $end
$var wire 1 7 w_not $end
$upscope $end
$scope module dff_2 $end
$var wire 1 $ clearN $end
$var wire 1 # clock $end
$var wire 1 8 inD $end
$var wire 1 9 outQ $end
$var wire 1 : w_and1 $end
$var wire 1 ; w_and2 $end
$var wire 1 < w_nor1 $end
$var wire 1 = w_nor2 $end
$var wire 1 > w_not $end
$upscope $end
$scope module dff_3 $end
$var wire 1 $ clearN $end
$var wire 1 # clock $end
$var wire 1 ? inD $end
$var wire 1 @ outQ $end
$var wire 1 A w_and1 $end
$var wire 1 B w_and2 $end
$var wire 1 C w_nor1 $end
$var wire 1 D w_nor2 $end
$var wire 1 E w_not $end
$upscope $end
$upscope $end
$upscope $end
$enddefinitions $end
#0
$dumpvars
0E
xD
xC
0B
0A
x@
1?
1>
x=
x<
0;
0:
x9
08
07
x6
x5
04
03
x2
11
00
x/
x.
0-
0,
x+
1*
bx )
b1011 (
b11110111111010111001111011000100 '
b100 &
b0 %
1$
0#
b1011 "
bx !
$end
#5
1+
12
1@
1.
15
1=
b1011 !
b1011 )
09
1C
0/
06
0<
0D
1-
14
1:
1B
1#
#10
0>
17
18
01
0-
04
0:
0B
b1101 "
b1101 (
b1011011101011101110110011010000 '
b100 &
b1 %
0#
#15
19
16
b1101 !
b1101 )
02
1<
05
0=
1-
13
1;
1B
1#
#20
07
11
0-
03
0;
0B
b1111 "
b1111 (
b1110001111111111111100110011100 '
b100 &
b10 %
0#
#25
b1111 !
b1111 )
12
15
06
1-
14
1;
1B
1#
#30
1>
10
08
0*
0-
04
0;
0B
b1010 "
b1010 (
b1001001110100111001000100101000 '
b100 &
b11 %
0#
#35
1/
0+
1=
b1010 !
b1010 )
09
0.
0<
1,
14
1:
1B
1#
#40
1E
0>
00
0?
18
1*
02
b0 !
b0 )
0@
0,
04
0:
0B
b111 "
b111 (
b10010111001010010011111101110100 '
b100 &
0$
b0 %
0#
#45
1.
1<
1D
0/
0=
0C
1-
14
1;
1A
1#
#50
0E
1?
0-
04
0;
0A
b1111 "
b1111 (
b11010100101110101000010000000 '
b100 &
b1 %
0#
#55
1C
0D
1-
14
1;
1B
1#
#60
1>
17
08
01
0-
04
0;
0B
b1001 "
b1001 (
b11111100101101101000001001100 '
b100 &
b10 %
0#
#65
16
1=
05
0<
1-
13
1:
1B
1#
#70
0-
03
0:
0B
b1011101100011111000101011011000 '
b100 &
b11 %
0#
#75
1-
13
1:
1B
1#
#80
0-
03
0:
0B
b100 %
0#
