older/verilog_code/cpe300/lab2_code/exp3b/exp3b.v
/*
    exp3_B, make a 2:1 mux, conditional operator
    use  assign Y = (s) ? a : b
*/

`timescale 1ns/1ns
`define STEP 10

module tb ();
    wire outY;
    reg sel;
    reg inA;
    reg inB;

    integer idx;
    reg [2:0] trans;

    mux21 DUT (
                .out_y(outY),
                .in_a(inA),
                .in_b(inB),
                .select(sel)
              );
    
    initial begin
        $dumpfile("wave.vcd");
        $dumpvars(0, tb);
        $write("\n2:1 MUX, 1-bit, assign Y = (~s) ? a : b\n\n");
        $write(" s  a  b  |  Y\n");
        $write("---------------\n");

        for (idx = 0; idx < 8; idx = idx + 1) begin
            trans = idx;
            sel = trans[2];
            inA = trans[1];
            inB = trans[0];
            # `STEP
            $write(" %b  %b  %b  |  %b\n",
                sel, inA, inB, outY);
        end

        # `STEP
        $write("\n\n\t\t ~ ~ ~ TEST COMPLETE ~ ~ ~\n\n");
        $finish;
    end

endmodule


////~~~~


module mux21 (
                output wire out_y,
                input wire select,
                input wire in_a,
                input wire in_b
             );
    assign out_y = (~select) ? in_a : in_b;
endmodule


////////~~~~~~~~END>  exp3b.v

older/verilog_code/cpe300/lab2_code/exp3a/wave.vcd
$date
	Wed Sep  8 10:40:40 2021
$end
$version
	Icarus Verilog
$end
$timescale
	1ns
$end
$scope module tb $end
$var wire 1 ! outY $end
$var reg 1 " inA $end
$var reg 1 # inB $end
$var reg 1 $ sel $end
$var reg 3 % trans [2:0] $end
$var integer 32 & idx [31:0] $end
$scope module DUT $end
$var wire 1 " in_a $end
$var wire 1 # in_b $end
$var wire 1 $ select $end
$var wire 1 ! out_y $end
$upscope $end
$upscope $end
$enddefinitions $end
#0
$dumpvars
b0 &
b0 %
0$
0#
0"
0!
$end
#10
1#
b1 %
b1 &
#20
0#
1!
1"
b10 %
b10 &
#30
1#
b11 %
b11 &
#40
0#
0"
0!
1$
b100 %
b100 &
#50
1!
1#
b101 %
b101 &
#60
0!
0#
1"
b110 %
b110 &
#70
1!
1#
b111 %
b111 &
#80
b1000 &
