verilog_code/cpe300/lab6_code/sum_combined/summing.v
/*
	summation algorithim, using GDP

    this is only made into a single file for academic requests
    make multiple files, giving each module a test bench for other uses
*/

`timescale 1ns/1ns 
`define HALF 5
`define START 0
`define STOP 23 // > 23 will overflow
`define DEBUG_TB -999
//`define DEBUG_CU -888
//`define DEBUG_DP -777


module tb();
	wire [7:0] result;
	wire done;
	reg [7:0] n_input;
	reg start;
    reg reset;
    reg clock;

	integer idx;
    integer check;
    reg [7:0] checkk;

    general_data_path GDP (
                            .result(result),
                            .done(done),
                            .n_input(n_input),
                            .start(start), 
                            .reset(reset), 
                            .clock(clock)
                        );

	always begin
		#`HALF;
		clock = ~clock;
	end
	
	initial begin
		$dumpfile("wave.vcd");
        $dumpvars(0, tb);
		$write("\n testing the summation algorithm on the GDP  ,  n = 0 : 22   ...n >= 23 overflows\n\n");
        $write("        input      |        result      |     expected\n");
        $write(" ----------------------------------------------------------\n");
		start = 1'b1;
		reset = 1'b1;
		clock = 1'b0;

        for (idx = `START; idx < `STOP; idx = idx + 1) begin
            reset = 1'b0;
            n_input = idx;

            while (done != 1'b1) begin
                #(`HALF + `HALF);
            end

            check = idx * (idx + 1) / 2;
            checkk = check;

            `ifdef DEBUG_TB
                $write("  {%2d}  %4b_%4b  |  %4b_%4b  {%3d}  |  {%3d}  %4b_%4b",
                    n_input, n_input[7:4], n_input[3:0], 
                    result[7:4], result[3:0], result,
                    check, checkk[7:4], checkk[3:0]);
                
                if (check == result) begin
                    $write("    --> Correct\n");
                end
                else begin
                    $write("    --> WRONG\n");
                end
            `endif

            reset = 1'b1;
            #(`HALF + `HALF);
        end

        #3;
        $write("\n\n\t\t ~ ~ ~ TEST COMPLETE ~ ~ ~  %7t  ns\n\n", $time);
		$finish;
	end
endmodule


////~~~~ top entity, combines control unit and data path
module general_data_path (
                            output wire [7:0] result,
                            output wire done,
                            input wire [7:0] n_input,
                            input wire start, 
                            input wire reset, 
                            input wire clock
                        );	
	wire IE;
    wire WE;
    wire [1:0] WA;
    wire RAE;
    wire [1:0] RAA;
    wire RBE;
    wire [1:0] RBA;
    wire [2:0] ALU;
    wire [1:0] SH;
    wire OE;
    wire n_is_0; 
	
    assign done = OE;

    control_unit CU (
                        .IE(IE), 
                        .WE(WE),
                        .WA(WA),
                        .RAE(RAE),
                        .RAA(RAA),
                        .RBE(RBE),
                        .RBA(RBA),
                        .ALU(ALU),
                        .SH(SH),
                        .OE(OE),
                        .n_is_0(n_is_0),
                        .start(start),
                        .reset(reset),
                        .clock(clock)
                    );

    data_path DP (
                    .n_is_0(n_is_0),
                    .result(result),
                    .n_input(n_input),
                    .IE(IE),
                    .WE(WE),
                    .WA(WA),
                    .RAE(RAE),
                    .RAA(RAA),
                    .RBE(RBE),
                    .RBA(RBA),
                    .ALU(ALU),
                    .SH(SH),
                    .OE(OE),
                    .clock(clock)
                );
endmodule


////~~~~ control unit applied to data path
module control_unit (
                        output wire IE, 
                        output wire WE,
                        output wire [1:0] WA,
                        output wire RAE,
                        output wire [1:0] RAA,
                        output wire RBE,
                        output wire [1:0] RBA,
                        output wire [2:0] ALU,
                        output wire [1:0] SH,
                        output wire OE,
                        input wire n_is_0,
                        input wire start,
                        input wire reset,
                        input wire clock
                    );

	reg [2:0] state;
	reg [2:0] n_state;

	parameter s0 = 3'b000;
	parameter s1 = 3'b001;
	parameter s2 = 3'b010;
	parameter s3 = 3'b011;
	parameter s4 = 3'b100;
	
	initial begin
        state = s0;
        n_state = s0;
    end
	
	always @ (posedge clock) begin
        if (reset == 1'b1) begin
            state = s0;
            n_state = s0;
        end
        else begin
            case(state)
                s0 : n_state = (start == 1'b1) ? s1 : s0;
                s1 : n_state = (n_is_0 == 1'b1) ? s4 : s2;
                s2 : n_state = s3;
                s3 : n_state = (n_is_0 == 1'b1) ? s4 : s2;
                s4 : n_state = (reset == 1'b1) ? s0 : s4;
                default : n_state = s0;
            endcase
            state <= n_state;
        end
	end
	
	assign IE = (state == s1);
		
	assign WE = (state == s0) || (state == s1) || (state == s2) || (state == s3);
	assign WA[1] = 1'b0;
	assign WA[0] = (state == s1) || (state == s3);
		
	assign RAE = (state == s0) || (state == s2) || (state == s3) || (state == s4);
	assign RAA[1] = 1'b0;
	assign RAA[0] = (state == s3);
		
	assign RBE = (state == s0) || (state == s2);
	assign RBA[1] = 1'b0;
	assign RBA[0] = (state == s2);
		
	assign ALU[2] = (state == s0) || (state == s2) || (state == s3);
	assign ALU[1] = (state == s3);
	assign ALU[0] = (state == s0) | (state == s3);
		
	assign SH[1] = 1'b0;
	assign SH[0] = 1'b0;
	assign OE = (state == s4);	

    `ifdef DEBUG_CU
        always @ (posedge clock) begin
            #`HALF;
			$write("\n st   nst  || IE | WE | WA | RAE | RAA | RBE | RBA | ALU | SH | OE || start | reset | n==0    %7t ns\n",
				$time);
			$write("-------------------------------------------------------------------------------------------\n");
			$write(" %3b  %3b  || %1b  | %1b  | %2b |  %1b  | %2b  |  %1b  | %2b  | %3b | %2b | %1b  ||   %1b   |   %1b   |  %1b\n", 
					state, n_state, IE,    WE,    WA,  RAE,    RAA,    RBE,   RBA,   ALU,   SH,   OE,   start, reset,   n_is_0);
        end
    `endif
endmodule


////~~~~ data path combining the 5 components 
module data_path (
                    output wire n_is_0,
                    output wire [7:0] result,
                    input wire [7:0] n_input,
                    input wire IE,
                    input wire WE,
                    input wire [1:0] WA,
                    input wire RAE,
                    input wire [1:0] RAA,
                    input wire RBE,
                    input wire [1:0] RBA,
                    input wire [2:0] ALU,
                    input wire [1:0] SH,
                    input wire OE,
                    input wire clock
                );

    parameter BLANK = 8'b0000_0000;  
    wire [7:0] from_mux;          
	reg [7:0] to_register_file;
    wire [7:0] rf_port_A;
    wire [7:0] rf_port_B;
    wire [7:0] from_alu;
    wire [7:0] from_shifter;
	
    /*
        This internal register completes the feedback.
        Unlike the other connections, it must be a register.
        It is very important and provides the initialization,
        along with proper transfer sequence.
    */
    initial begin
        to_register_file = BLANK;
    end
    always @ (*) begin
        to_register_file = from_mux;
    end
	
    /*
        This is the probe right under the MUX.
        It won't fail if you move states correctly.
        Don't get too crazy with the logic checks
    */
	assign n_is_0 = (from_mux == 8'b0000_0000); 

    c1_mux comp1 (
                    .from_mux(from_mux),
                    .new_data(n_input), 
                    .feedback(from_shifter),
                    .IE(IE)
                );

    c2_register_file comp2 (
                            .port_A(rf_port_A),
                            .port_B(rf_port_B),     
                            .from_mux(to_register_file),
                            .WE(WE),                
                            .WA(WA),          
                            .RAE(RAE),    
                            .RAA(RAA),         
                            .RBE(RBE),            
                            .RBA(RBA),      
                            .clock(clock)
                        ); 

    c3_alu comp3 (
                    .from_alu(from_alu),
                    .A_bus(rf_port_A),
                    .B_bus(rf_port_B),
                    .ALU(ALU)
                );

    c4_shifter comp4 (
                        .from_shifter(from_shifter),
                        .from_alu(from_alu),
                        .SH(SH)
                    );


    c5_triBuff comp5 (
                        .result(result), 
                        .from_shifter(from_shifter), 
                        .OE(OE)
                    );
    
    `ifdef DEBUG_DP
        always @ (negedge clock) begin
            #1;
            $write("\n ************************************************\n");
            $write(" {data_path}                               %7t ns\n", $time);
            $write("               n_is_0:  %1b\n", n_is_0);
            $write(" -------------------------\n");
            $write("                   IE:  %1b\n", IE);
            $write("  mux[0], shifter_out:  %4b_%4b\n", from_shifter[7:4], from_shifter[3:0]);
            $write("         mux[1], n_in:  %4b_%4b\n", n_input[7:4], n_input[3:0]);
            $write("         mux out, nnn:  %4b_%4b\n", from_mux[7:4], from_mux[3:0]);
            $write(" ---------------------------------\n");
            $write("               rf_inp:  %4b_%4b\n", to_register_file[7:4], to_register_file[3:0]);
            $write(" WE:   %1b  ,  WA:   %2b\n", WE, WA);
            $write(" RAE:  %1b  ,  RAA:  %2b\n", RAE, RAA);
            $write(" RBE:  %1b  ,  RBA:  %2b\n", RBE, RBA);
            $write(" reg[00]:  %4b_%4b \"sum\"\n", comp2.internal[2'b00][7:4], comp2.internal[2'b00][3:0]);
            $write(" reg[01]:  %4b_%4b \"n\"\n"  , comp2.internal[2'b01][7:4], comp2.internal[2'b01][3:0]);
            $write(" reg[10]:  %4b_%4b\n"        , comp2.internal[2'b10][7:4], comp2.internal[2'b10][3:0]);
            $write(" reg[11]:  %4b_%4b\n"        , comp2.internal[2'b11][7:4], comp2.internal[2'b11][3:0]);
            $write("               port A:  %4b_%4b\n", rf_port_A[7:4], rf_port_A[3:0]);
            $write("               port B:  %4b_%4b\n", rf_port_B[7:4], rf_port_B[3:0]);
            $write(" --------------------------------------\n");
            $write("        alu operation:  %3b\n", ALU);
            $write("           alu output:  %4b_%4b\n", from_alu[7:4], from_alu[3:0]);
            $write(" ---------------------------------\n");
            $write("    shifter operation:  %3b\n", SH);
            $write("       shifter output:  %4b_%4b\n", from_shifter[7:4], from_shifter[3:0]);
            $write(" ---------------------------------\n");
            $write("                   OE:  %1b\n", OE);
            $write("               result:  %4b_%4b", result[7:4], result[3:0]);
            if (OE == 1'b1) $write("   !!!SUCCESS!!!\n");
            else $write("      ...working\n");
            $write(" ************************************************\n");
        end
    `endif
endmodule


////~~~~ 2-to-1 mux, 8 bits, component 1 of 5
module c1_mux (
                    output reg [7:0] from_mux,
                    input wire [7:0] new_data, 
                    input wire [7:0] feedback,
                    input wire IE
                );
	
	always @ (*) begin
        from_mux = (IE == 1'b1) ? new_data : feedback;
    end
endmodule


////~~~~ register file, component 2 of 5
module c2_register_file(
                            output wire [7:0] port_A,     // value assigned to port A
                            output wire [7:0] port_B,     // value assigned to port B
                            input wire [7:0] from_mux,    // bus after MUX selection
                            input wire WE,                // write enable
                            input wire [1:0] WA,          // write address
                            input wire RAE,               // port A read enable
                            input wire [1:0] RAA,         // port A Read address 
                            input wire RBE,               // port B read enable
                            input wire [1:0] RBA,         // port B read address
                            input wire clock
                        ); 
	
    parameter BLANK = 8'b0000_0000;

    // x4 8-bit registers "4x8"
	reg [7:0] internal [3:0]; 

    // only write if WE is active
	always @ (posedge clock) begin
        if (WE == 1'b1) internal[WA] <= from_mux;
    end
     
    // reading to ports is done in combination, if enabled
    assign port_A = (RAE == 1'b1) ? internal[RAA] : BLANK; 
    assign port_B = (RBE == 1'b1) ? internal[RBA] : BLANK;
endmodule


////~~~~ ALU, component 3 of 5
module c3_alu (
                output reg [7:0] from_alu,
                input wire [7:0] A_bus,
                input wire [7:0] B_bus,
                input wire [2:0] ALU
            );

    parameter pass_A = 3'b000;     // bus A passes through
    parameter A_and_B = 3'b001;    // bitwise AND
    parameter A_or_B = 3'b010;     // bitwise OR
    parameter not_A = 3'b011;      // negate bus A
    parameter A_add_B = 3'b100;    // addition
    parameter A_sub_B = 3'b101;    // subtraction
    parameter inc_A = 3'b110;      // increment bus A
    parameter dec_A = 3'b111;      // decrement bus A

    always @ (*) begin 
        case(ALU) 
            pass_A  : from_alu = A_bus;                  
            A_and_B : from_alu = A_bus & B_bus;                  
            A_or_B  : from_alu = A_bus | B_bus; 
            not_A   : from_alu = ~A_bus;
            A_add_B : from_alu = A_bus + B_bus;
            A_sub_B : from_alu = A_bus - B_bus;
            inc_A   : from_alu = A_bus + 1'b1;
            dec_A   : from_alu = A_bus - 1'b1;                
        endcase
    end
endmodule


////~~~~ shifter, componenet 4 of 5
module c4_shifter (
                    output reg [7:0] from_shifter,
                    input wire [7:0] from_alu,
                    input wire [1:0] SH
                );

    parameter PASS = 2'b00;      // pass through
    parameter LEFT = 2'b01;      // left shift and fill with 0's
    parameter RIGHT = 2'b10;     // right shift and fill with 0's
    parameter ROTATE = 2'b11;    // rotate right

    always @ (*) begin 
        case(SH) 
            PASS   : from_shifter = from_alu;                  
            LEFT   : from_shifter = from_alu << 1;                 
            RIGHT  : from_shifter = from_alu >> 1;
            ROTATE : from_shifter = {from_alu[6:0], from_alu[7]};                    
        endcase
    end
endmodule


////~~~~ final output buffer, componenet 5 of 5
module c5_triBuff (
                    output reg [7:0] result, 
                    input wire [7:0] from_shifter, 
                    input wire OE
                );

	always @ (*) begin
        result = (OE == 1'b1) ? from_shifter : 8'bzzzz_zzzz;
    end		
endmodule


////////~~~~~~~~END>  summing.v

verilog_code/cpe300/lab6_code/sum_combined/wave.vcd
$date
	Wed Oct  6 22:54:58 2021
$end
$version
	Icarus Verilog
$end
$timescale
	1ns
$end
$scope module tb $end
$var wire 8 ! result [7:0] $end
$var wire 1 " done $end
$var reg 8 # checkk [7:0] $end
$var reg 1 $ clock $end
$var reg 8 % n_input [7:0] $end
$var reg 1 & reset $end
$var reg 1 ' start $end
$var integer 32 ( check [31:0] $end
$var integer 32 ) idx [31:0] $end
$scope module GDP $end
$var wire 1 $ clock $end
$var wire 1 " done $end
$var wire 8 * n_input [7:0] $end
$var wire 1 & reset $end
$var wire 1 ' start $end
$var wire 8 + result [7:0] $end
$var wire 1 , n_is_0 $end
$var wire 1 - WE $end
$var wire 2 . WA [1:0] $end
$var wire 2 / SH [1:0] $end
$var wire 1 0 RBE $end
$var wire 2 1 RBA [1:0] $end
$var wire 1 2 RAE $end
$var wire 2 3 RAA [1:0] $end
$var wire 1 4 OE $end
$var wire 1 5 IE $end
$var wire 3 6 ALU [2:0] $end
$scope module CU $end
$var wire 1 2 RAE $end
$var wire 1 0 RBE $end
$var wire 1 - WE $end
$var wire 1 $ clock $end
$var wire 1 & reset $end
$var wire 1 ' start $end
$var wire 1 , n_is_0 $end
$var wire 2 7 WA [1:0] $end
$var wire 2 8 SH [1:0] $end
$var wire 2 9 RBA [1:0] $end
$var wire 2 : RAA [1:0] $end
$var wire 1 4 OE $end
$var wire 1 5 IE $end
$var wire 3 ; ALU [2:0] $end
$var reg 3 < n_state [2:0] $end
$var reg 3 = state [2:0] $end
$upscope $end
$scope module DP $end
$var wire 3 > ALU [2:0] $end
$var wire 1 5 IE $end
$var wire 1 4 OE $end
$var wire 2 ? RAA [1:0] $end
$var wire 1 2 RAE $end
$var wire 2 @ RBA [1:0] $end
$var wire 1 0 RBE $end
$var wire 2 A SH [1:0] $end
$var wire 2 B WA [1:0] $end
$var wire 1 - WE $end
$var wire 1 $ clock $end
$var wire 8 C n_input [7:0] $end
$var wire 8 D rf_port_B [7:0] $end
$var wire 8 E rf_port_A [7:0] $end
$var wire 8 F result [7:0] $end
$var wire 1 , n_is_0 $end
$var wire 8 G from_shifter [7:0] $end
$var wire 8 H from_mux [7:0] $end
$var wire 8 I from_alu [7:0] $end
$var reg 8 J to_register_file [7:0] $end
$scope module comp1 $end
$var wire 1 5 IE $end
$var wire 8 K new_data [7:0] $end
$var wire 8 L feedback [7:0] $end
$var reg 8 M from_mux [7:0] $end
$upscope $end
$scope module comp2 $end
$var wire 2 N RAA [1:0] $end
$var wire 1 2 RAE $end
$var wire 2 O RBA [1:0] $end
$var wire 1 0 RBE $end
$var wire 2 P WA [1:0] $end
$var wire 1 - WE $end
$var wire 1 $ clock $end
$var wire 8 Q from_mux [7:0] $end
$var wire 8 R port_B [7:0] $end
$var wire 8 S port_A [7:0] $end
$upscope $end
$scope module comp3 $end
$var wire 3 T ALU [2:0] $end
$var wire 8 U A_bus [7:0] $end
$var wire 8 V B_bus [7:0] $end
$var reg 8 W from_alu [7:0] $end
$upscope $end
$scope module comp4 $end
$var wire 2 X SH [1:0] $end
$var wire 8 Y from_alu [7:0] $end
$var reg 8 Z from_shifter [7:0] $end
$upscope $end
$scope module comp5 $end
$var wire 1 4 OE $end
$var wire 8 [ from_shifter [7:0] $end
$var reg 8 \ result [7:0] $end
$upscope $end
$upscope $end
$upscope $end
$upscope $end
$enddefinitions $end
#0
$dumpvars
bz \
bx [
bx Z
bx Y
b0 X
bx W
bx V
bx U
b101 T
bx S
bx R
b0 Q
b0 P
b0 O
b0 N
bx M
bx L
b0 K
b0 J
bx I
bx H
bx G
bz F
bx E
bx D
b0 C
b0 B
b0 A
b0 @
b0 ?
b101 >
b0 =
b0 <
b101 ;
b0 :
b0 9
b0 8
b0 7
b101 6
05
04
b0 3
12
b0 1
10
b0 /
b0 .
1-
x,
bz +
b0 *
b0 )
bx (
1'
0&
b0 %
0$
bx #
0"
bz !
$end
#5
02
b0 G
b0 L
b0 Z
b0 [
b0 I
b0 W
b0 Y
1,
b0 H
b0 M
b1 .
b1 7
b1 B
b1 P
00
b0 6
b0 ;
b0 >
b0 T
b0 E
b0 S
b0 U
b0 D
b0 R
b0 V
15
b1 =
b1 <
1$
#10
0$
#15
0-
b0 .
b0 7
b0 B
b0 P
12
b0 !
b0 +
b0 F
b0 \
05
1"
14
b100 =
b100 <
1$
#20
0$
1&
b0 #
b0 (
#25
1-
12
10
b101 6
b101 ;
b101 >
b101 T
bz !
bz +
bz F
bz \
b0 <
0"
04
b0 =
1$
#30
0$
b1 %
b1 *
b1 C
b1 K
0&
b1 )
#35
02
b1 J
b1 Q
0,
b1 H
b1 M
b1 .
b1 7
b1 B
b1 P
00
b0 6
b0 ;
b0 >
b0 T
15
b1 =
b1 <
1$
#40
0$
#45
b1 G
b1 L
b1 Z
b1 [
b1 I
b1 W
b1 Y
12
b1 D
b1 R
b1 V
b1 J
b1 Q
b100 6
b100 ;
b100 >
b100 T
0,
b1 H
b1 M
b0 .
b0 7
b0 B
b0 P
10
05
b1 1
b1 9
b1 @
b1 O
b10 =
b10 <
1$
#50
0$
#55
1,
b0 J
b0 Q
b0 D
b0 R
b0 V
b0 H
b0 M
b0 G
b0 L
b0 Z
b0 [
b1 .
b1 7
b1 B
b1 P
b1 E
b1 S
b1 U
00
b0 I
b0 W
b0 Y
b1 3
b1 :
b1 ?
b1 N
b0 1
b0 9
b0 @
b0 O
b111 6
b111 ;
b111 >
b111 T
b11 =
b11 <
1$
#60
0$
#65
b1 J
b1 Q
0,
b1 H
b1 M
b1 G
b1 L
b1 Z
b1 [
0-
b0 .
b0 7
b0 B
b0 P
b1 I
b1 W
b1 Y
b1 !
b1 +
b1 F
b1 \
b0 3
b0 :
b0 ?
b0 N
b0 6
b0 ;
b0 >
b0 T
1"
14
b100 =
b100 <
1$
#70
0$
1&
b1 #
b1 (
#75
b0 J
b0 Q
1,
b0 H
b0 M
1-
b1 E
b1 S
b1 U
b1 D
b1 R
b1 V
b0 G
b0 L
b0 Z
b0 [
b0 I
b0 W
b0 Y
12
10
b101 6
b101 ;
b101 >
b101 T
bz !
bz +
bz F
bz \
b0 <
0"
04
b0 =
1$
#80
0$
b10 %
b10 *
b10 C
b10 K
0&
b10 )
#85
02
b10 J
b10 Q
0,
b10 H
b10 M
b1 .
b1 7
b1 B
b1 P
00
b0 6
b0 ;
b0 >
b0 T
b0 E
b0 S
b0 U
b0 D
b0 R
b0 V
15
b1 =
b1 <
1$
#90
0$
#95
b10 G
b10 L
b10 Z
b10 [
b10 I
b10 W
b10 Y
12
b10 D
b10 R
b10 V
b10 J
b10 Q
b100 6
b100 ;
b100 >
b100 T
0,
b10 H
b10 M
b0 .
b0 7
b0 B
b0 P
10
05
b1 1
b1 9
b1 @
b1 O
b10 =
b10 <
1$
#100
0$
#105
b1 J
b1 Q
b0 D
b0 R
b0 V
b1 H
b1 M
b1 G
b1 L
b1 Z
b1 [
b1 .
b1 7
b1 B
b1 P
00
b1 I
b1 W
b1 Y
b10 E
b10 S
b10 U
b1 3
b1 :
b1 ?
b1 N
b0 1
b0 9
b0 @
b0 O
b111 6
b111 ;
b111 >
b111 T
b11 =
b11 <
1$
#110
0$
#115
b10 E
b10 S
b10 U
b11 J
b11 Q
b1 D
b1 R
b1 V
b11 H
b11 M
12
b11 G
b11 L
b11 Z
b11 [
1-
b0 .
b0 7
b0 B
b0 P
10
b11 I
b11 W
b11 Y
b0 3
b0 :
b0 ?
b0 N
b1 1
b1 9
b1 @
b1 O
b100 6
b100 ;
b100 >
b100 T
b10 =
b10 <
1$
#120
0$
#125
b0 J
b0 Q
1,
b0 H
b0 M
b0 G
b0 L
b0 Z
b0 [
b1 .
b1 7
b1 B
b1 P
00
b0 D
b0 R
b0 V
b0 I
b0 W
b0 Y
b1 E
b1 S
b1 U
b1 3
b1 :
b1 ?
b1 N
b0 1
b0 9
b0 @
b0 O
b111 6
b111 ;
b111 >
b111 T
b11 =
b11 <
1$
#130
0$
#135
b11 J
b11 Q
0,
b11 H
b11 M
b11 G
b11 L
b11 Z
b11 [
0-
b0 .
b0 7
b0 B
b0 P
b11 E
b11 S
b11 U
b11 I
b11 W
b11 Y
b11 !
b11 +
b11 F
b11 \
b0 3
b0 :
b0 ?
b0 N
b0 6
b0 ;
b0 >
b0 T
1"
14
b100 =
b100 <
1$
#140
0$
1&
b11 #
b11 (
#145
b0 J
b0 Q
1,
b0 H
b0 M
1-
b11 E
b11 S
b11 U
b11 D
b11 R
b11 V
b0 G
b0 L
b0 Z
b0 [
b0 I
b0 W
b0 Y
12
10
b101 6
b101 ;
b101 >
b101 T
bz !
bz +
bz F
bz \
b0 <
0"
04
b0 =
1$
#150
0$
b11 %
b11 *
b11 C
b11 K
0&
b11 )
#155
02
b11 J
b11 Q
b0 E
b0 S
b0 U
b0 D
b0 R
b0 V
0,
b11 H
b11 M
b1 .
b1 7
b1 B
b1 P
00
b0 6
b0 ;
b0 >
b0 T
15
b1 =
b1 <
1$
#160
0$
#165
b11 G
b11 L
b11 Z
b11 [
b11 I
b11 W
b11 Y
12
b11 D
b11 R
b11 V
b11 J
b11 Q
b100 6
b100 ;
b100 >
b100 T
0,
b11 H
b11 M
b0 .
b0 7
b0 B
b0 P
10
05
b1 1
b1 9
b1 @
b1 O
b10 =
b10 <
1$
#170
0$
#175
b10 J
b10 Q
b0 D
b0 R
b0 V
b10 H
b10 M
b10 G
b10 L
b10 Z
b10 [
b1 .
b1 7
b1 B
b1 P
b11 E
b11 S
b11 U
00
b10 I
b10 W
b10 Y
b1 3
b1 :
b1 ?
b1 N
b0 1
b0 9
b0 @
b0 O
b111 6
b111 ;
b111 >
b111 T
b11 =
b11 <
1$
#180
0$
#185
b11 E
b11 S
b11 U
b101 J
b101 Q
b10 D
b10 R
b10 V
b101 H
b101 M
12
b101 G
b101 L
b101 Z
b101 [
1-
b0 .
b0 7
b0 B
b0 P
10
b101 I
b101 W
b101 Y
b0 3
b0 :
b0 ?
b0 N
b1 1
b1 9
b1 @
b1 O
b100 6
b100 ;
b100 >
b100 T
b10 =
b10 <
1$
#190
0$
#195
b1 J
b1 Q
b1 H
b1 M
b1 G
b1 L
b1 Z
b1 [
b1 .
b1 7
b1 B
b1 P
b10 E
b10 S
b10 U
00
b0 D
b0 R
b0 V
b1 I
b1 W
b1 Y
b1 3
b1 :
b1 ?
b1 N
b0 1
b0 9
b0 @
b0 O
b111 6
b111 ;
b111 >
b111 T
b11 =
b11 <
1$
#200
0$
#205
b110 J
b110 Q
b1 D
b1 R
b1 V
b110 H
b110 M
12
b110 G
b110 L
b110 Z
b110 [
1-
b0 .
b0 7
b0 B
b0 P
10
b110 I
b110 W
b110 Y
b101 E
b101 S
b101 U
b0 3
b0 :
b0 ?
b0 N
b1 1
b1 9
b1 @
b1 O
b100 6
b100 ;
b100 >
b100 T
b10 =
b10 <
1$
#210
0$
#215
1,
b0 J
b0 Q
b0 H
b0 M
b0 G
b0 L
b0 Z
b0 [
b1 .
b1 7
b1 B
b1 P
b1 E
b1 S
b1 U
00
b0 D
b0 R
b0 V
b0 I
b0 W
b0 Y
b1 3
b1 :
b1 ?
b1 N
b0 1
b0 9
b0 @
b0 O
b111 6
b111 ;
b111 >
b111 T
b11 =
b11 <
1$
#220
0$
#225
b110 J
b110 Q
0,
b110 H
b110 M
b110 G
b110 L
b110 Z
b110 [
0-
b0 .
b0 7
b0 B
b0 P
b110 I
b110 W
b110 Y
b110 !
b110 +
b110 F
b110 \
b110 E
b110 S
b110 U
b0 3
b0 :
b0 ?
b0 N
b0 6
b0 ;
b0 >
b0 T
1"
14
b100 =
b100 <
1$
#230
0$
1&
b110 #
b110 (
#235
b0 J
b0 Q
1,
b0 H
b0 M
1-
b110 E
b110 S
b110 U
b110 D
b110 R
b110 V
b0 G
b0 L
b0 Z
b0 [
b0 I
b0 W
b0 Y
12
10
b101 6
b101 ;
b101 >
b101 T
bz !
bz +
bz F
bz \
b0 <
0"
04
b0 =
1$
#240
0$
b100 %
b100 *
b100 C
b100 K
0&
b100 )
#245
02
b100 J
b100 Q
0,
b100 H
b100 M
b1 .
b1 7
b1 B
b1 P
00
b0 6
b0 ;
b0 >
b0 T
b0 E
b0 S
b0 U
b0 D
b0 R
b0 V
15
b1 =
b1 <
1$
#250
0$
#255
b100 G
b100 L
b100 Z
b100 [
b100 I
b100 W
b100 Y
12
b100 D
b100 R
b100 V
b100 J
b100 Q
b100 6
b100 ;
b100 >
b100 T
0,
b100 H
b100 M
b0 .
b0 7
b0 B
b0 P
10
05
b1 1
b1 9
b1 @
b1 O
b10 =
b10 <
1$
#260
0$
#265
b11 J
b11 Q
b0 D
b0 R
b0 V
b11 H
b11 M
b11 G
b11 L
b11 Z
b11 [
b1 .
b1 7
b1 B
b1 P
00
b11 I
b11 W
b11 Y
b100 E
b100 S
b100 U
b1 3
b1 :
b1 ?
b1 N
b0 1
b0 9
b0 @
b0 O
b111 6
b111 ;
b111 >
b111 T
b11 =
b11 <
1$
#270
0$
#275
b100 E
b100 S
b100 U
b111 J
b111 Q
b11 D
b11 R
b11 V
b111 H
b111 M
12
b111 G
b111 L
b111 Z
b111 [
1-
b0 .
b0 7
b0 B
b0 P
10
b111 I
b111 W
b111 Y
b0 3
b0 :
b0 ?
b0 N
b1 1
b1 9
b1 @
b1 O
b100 6
b100 ;
b100 >
b100 T
b10 =
b10 <
1$
#280
0$
#285
b10 J
b10 Q
b10 H
b10 M
b10 G
b10 L
b10 Z
b10 [
b1 .
b1 7
b1 B
b1 P
00
b0 D
b0 R
b0 V
b10 I
b10 W
b10 Y
b11 E
b11 S
b11 U
b1 3
b1 :
b1 ?
b1 N
b0 1
b0 9
b0 @
b0 O
b111 6
b111 ;
b111 >
b111 T
b11 =
b11 <
1$
#290
0$
#295
b1001 J
b1001 Q
b10 D
b10 R
b10 V
b1001 H
b1001 M
12
b1001 G
b1001 L
b1001 Z
b1001 [
1-
b0 .
b0 7
b0 B
b0 P
b111 E
b111 S
b111 U
10
b1001 I
b1001 W
b1001 Y
b0 3
b0 :
b0 ?
b0 N
b1 1
b1 9
b1 @
b1 O
b100 6
b100 ;
b100 >
b100 T
b10 =
b10 <
1$
#300
0$
#305
b1 J
b1 Q
b1 H
b1 M
b1 G
b1 L
b1 Z
b1 [
b1 .
b1 7
b1 B
b1 P
00
b0 D
b0 R
b0 V
b1 I
b1 W
b1 Y
b10 E
b10 S
b10 U
b1 3
b1 :
b1 ?
b1 N
b0 1
b0 9
b0 @
b0 O
b111 6
b111 ;
b111 >
b111 T
b11 =
b11 <
1$
#310
0$
#315
b1010 J
b1010 Q
b1 D
b1 R
b1 V
b1010 H
b1010 M
12
b1010 G
b1010 L
b1010 Z
b1010 [
1-
b0 .
b0 7
b0 B
b0 P
b1001 E
b1001 S
b1001 U
10
b1010 I
b1010 W
b1010 Y
b0 3
b0 :
b0 ?
b0 N
b1 1
b1 9
b1 @
b1 O
b100 6
b100 ;
b100 >
b100 T
b10 =
b10 <
1$
#320
0$
#325
b0 J
b0 Q
1,
b0 H
b0 M
b0 G
b0 L
b0 Z
b0 [
b1 .
b1 7
b1 B
b1 P
00
b0 D
b0 R
b0 V
b0 I
b0 W
b0 Y
b1 E
b1 S
b1 U
b1 3
b1 :
b1 ?
b1 N
b0 1
b0 9
b0 @
b0 O
b111 6
b111 ;
b111 >
b111 T
b11 =
b11 <
1$
#330
0$
#335
b1010 J
b1010 Q
0,
b1010 H
b1010 M
b1010 G
b1010 L
b1010 Z
b1010 [
0-
b0 .
b0 7
b0 B
b0 P
b1010 E
b1010 S
b1010 U
b1010 I
b1010 W
b1010 Y
b1010 !
b1010 +
b1010 F
b1010 \
b0 3
b0 :
b0 ?
b0 N
b0 6
b0 ;
b0 >
b0 T
1"
14
b100 =
b100 <
1$
#340
0$
1&
b1010 #
b1010 (
#345
b0 J
b0 Q
1,
b0 H
b0 M
1-
b1010 E
b1010 S
b1010 U
b1010 D
b1010 R
b1010 V
b0 G
b0 L
b0 Z
b0 [
b0 I
b0 W
b0 Y
12
10
b101 6
b101 ;
b101 >
b101 T
bz !
bz +
bz F
bz \
b0 <
0"
04
b0 =
1$
#350
0$
b101 %
b101 *
b101 C
b101 K
0&
b101 )
#355
02
b101 J
b101 Q
b0 E
b0 S
b0 U
b0 D
b0 R
b0 V
0,
b101 H
b101 M
b1 .
b1 7
b1 B
b1 P
00
b0 6
b0 ;
b0 >
b0 T
15
b1 =
b1 <
1$
#360
0$
#365
b101 G
b101 L
b101 Z
b101 [
b101 I
b101 W
b101 Y
12
b101 D
b101 R
b101 V
b101 J
b101 Q
b100 6
b100 ;
b100 >
b100 T
0,
b101 H
b101 M
b0 .
b0 7
b0 B
b0 P
10
05
b1 1
b1 9
b1 @
b1 O
b10 =
b10 <
1$
#370
0$
#375
b100 J
b100 Q
b0 D
b0 R
b0 V
b100 H
b100 M
b100 G
b100 L
b100 Z
b100 [
b1 .
b1 7
b1 B
b1 P
b101 E
b101 S
b101 U
00
b100 I
b100 W
b100 Y
b1 3
b1 :
b1 ?
b1 N
b0 1
b0 9
b0 @
b0 O
b111 6
b111 ;
b111 >
b111 T
b11 =
b11 <
1$
#380
0$
