older/verilog_code/cpe300/hw4/correct/testb11.v
/*
	summation algorithim, using GDP
	!!! use "my_GDP.v" for Altera products (test bench not applicable)
*/

`timescale 1ns/1ns         // simulation only
`define STEP 10            // combonational time step
`define DEBUG_wave -888    // dumpfile->dumpvars->GTKwave


module testb11;
	wire displayRes;
	wire [7:0] sum;
	reg [7:0] nIn;
	reg start, restart, clk;

	integer i;
	
	GDP main (
				.Sum(sum), 
	          	.start(start), 
	          	.restart(restart), 
	          	.clk(clk), 
	          	.n(nIn),
	          	.done(displayRes)
			);

	always begin
		#2;
		clk = ~clk;
	end
	
	initial begin
		`ifdef DEBUG_wave
            $dumpfile("wave.vcd");
            $dumpvars(0, testb11);
        `endif
		$write("\n testing the summation algorithm on the GDP  ,  n = 0 : 22\n\n");
		start = 1'b1;
		restart = 1'b1;
		clk = 1'b0;
	end

	always begin
		// 22 is a max number //not causing overflow in summation
		for(i = 0; i < 23; i = i + 1)  begin
			nIn <= i;
			start = 1'b0;
			#40 restart = 1'b1;
			
			// Waiting for the work to finish, DispRes (Done)=1
			while(displayRes != 1'b1) begin #5; end
				
			$write(" Input:  %2d  ,  Result:  %3d  ,  Expected:  %3d",
				nIn, sum, i*(i+1)/2);
				
			if(sum == (i*(i+1)/2))  //calculates the sum of 1,2,3,4,5...n
				$display("    -->  Correct!");
			else
				$display("    -->  Incorrect!");
				 
			restart = 1'b0;
			start = 1'b1;
		end
		#`STEP;
		$write("\n\n\t\t ~ ~ ~ TEST COMPLETE ~ ~ ~  %3t  ns\n\n", $time);
		$finish;
	end
endmodule



// Code your design here
// top module combines all other modules, including DP and CU
// Note: nEqZero is the input N=0, that is false condition is //evaluated, just for the convenience
module GDP(Sum, start, restart, clk, n, done);	
	input start, clk, restart;
	input [7:0] n;
	output [7:0] Sum;
	output done;
	
	wire WE, RAE, RBE, OE, nEqZero, IE;
	wire [1:0] WA, RAA, RBA, SH;
	wire [2:0] ALU;
	
 	CU control (IE, WE, WA, RAE, RAA, RBE, RBA, ALU, SH, OE, ~start, clk, ~restart, nEqZero);
	DP datapath (nEqZero, Sum, n, clk, IE, WE, WA, RAE, RAA, RBE, RBA, ALU, SH, OE);
	assign done = OE;
endmodule


////~~~~ control unit
module CU(IE, WE, WA, RAE, RAA, RBE, RBA, ALU, SH, OE, start, clk, restart, nEqZero);

	input start, clk, restart;
	output IE, WE, RAE, RBE, OE;
	output [1:0] WA, RAA, RBA, SH;
	output [2:0] ALU;
	
	input wire nEqZero;
	reg [2:0] state;
	reg [2:0] nextstate;

	parameter S0 = 3'b000;
	parameter S1 = 3'b001;
	parameter S2 = 3'b010;
	parameter S3 = 3'b011;
	parameter S4 = 3'b100;
	
	initial
		state = S0;
	
	// State register
	always @ (posedge clk)
	begin
		state <= nextstate;
	end
	// NS logic
	always @ (*)
		case(state)
			S0: 	if(start) nextstate = S1;
					else 	nextstate = S0;
			S1:	if(nEqZero) nextstate = S4;
					else 	nextstate = S2;
			S2:	nextstate = S3;
			S3:	if(nEqZero) nextstate = S4;
					else 	nextstate = S2;
			S4:	if(restart)	nextstate = S0;
					else	nextstate = S4;
			default: nextstate = S0;
		endcase
		
		// output logic
	assign IE = state == S1;
		
	assign WE = ~state[2];
	assign WA[1] = 0;
	assign WA[0] = ~state[2] && state[0];
		
	assign RAE = ~state[2] && state[1] || ~state[1] && ~state[0];
	assign RAA[1] = 0;
	assign RAA[0] = state == S3;
		
	assign RBE = ~state[2] && ~state[0];
	assign RBA[1] = 0;
	assign RBA[0] = state == S2;
		
	assign ALU[2] = ~state[2] && ~state[0] || ~state[2] && state[1];
	assign ALU[1] = state == S3;
	assign ALU[0] = state == S0 || state == S3;
		
	assign SH[1] = 0;
	assign SH[0] = 0;
	assign OE = state == S4;	
endmodule


////~~~~ data path
module DP(nEQZero, sum, nIn, clk, IE, WE, WA, RAE, RAA, RBE, RBA, ALU, SH, OE);
	input clk, IE, WE, RAE, RBE, OE;
	input [1:0] WA, RAA, RBA, SH;
	input [2:0] ALU;
	input [7:0] nIn;
	
	output nEQZero;
	output wire [7:0] sum;
	
	reg [7:0] rfIn;
	wire [7:0] RFa, RFb, aluOut, shOut, n;
	
	 initial 
	 rfIn = 0;
	 
	always @ (*)
	 rfIn = n;
	
	mux8 muxs (n, shOut, nIn, IE);
	Regfile RF (clk, RAA, RFa, RBA, RFb, WE, WA, rfIn, RAE, RBE);
	alu theALU (aluOut, RFa, RFb, ALU);
	shifter SHIFT (shOut, aluOut, SH);
	buff buffer1 (sum, shOut, OE);
	
	assign nEQZero = (n == 0);  //note: checks the false //condition
endmodule


////~~~~ 2-to-1 mux (sel = 0 -> choose a)
module mux8(result, a, b, sel);

	output reg[7:0] result;
	input[7:0] a;
	input[7:0] b;
	input sel;
	
	always @(*)
		if(sel == 0)
			result = a;
		else
			result = b;
endmodule


////~~~~ register file
module Regfile(
                    input clk,
                    input   [1:0]  RAA,       // Port A Read address 
                    output  [7:0] ReadA,      // Port A
                    input   [1:0] RBA,        // Port B Read address 
                    output  [7:0] ReadB,      // Port B
                    input   WE,               // Write enable 
                    input   [1:0] WA,         // Write port register address
                    input   [7:0] INPUT_D,    // Write data port
                    input   RAE,              // Port A decoder enable
                    input   RBE               // Port B decoder enable
                ); 
	// width          depth
	reg [7:0]  REG_F [0:3];

// Write only when WE is asserted
	always @(posedge clk) 
		if (WE == 1)  REG_F[WA] <= INPUT_D;
     
  //reading to Port A and B, combinational
  assign ReadA = (RAE)? REG_F [RAA]:0; 
  assign ReadB = (RBE)? REG_F [RBA]:0; 
endmodule


////~~~~ ALU
module alu (out,a,b,sel);
    input [7:0] a,b;
    input [2:0] sel; 
    output [7:0] out;
    reg [7:0] out;

    always @ (*) 
    begin 
        case(sel) 
            3'b000: out=a;                  
            3'b001: out=a&b;                  
            3'b010: out=a|b;                  
            3'b011: out=!a;                  
            3'b100: out=a+b;                  
            3'b101: out=a-b;     
            3'b110: out=a+1;                 
            3'b111: out=a-1;                  
        endcase
    end
endmodule


////~~~~ shifter
module shifter (out,a,sh);
    input [7:0] a;
    input [1:0] sh;
    output reg [7:0] out;

    always @ (*) 
    begin 
        case(sh) 
            3'b00: out=a;                  
            3'b01: out=a << 1;                  
            3'b10: out=a >> 1;                  
            3'b11: out={a[6],a[5],a[4],a[3],a[2],a[1],a[0], a[7]} ;
        endcase
    end
endmodule


////~~~~ final buffer
module buff(output reg [7:0] result, input[7:0] a, input buf1);
	always @(*)
		if(buf1 == 1)
			result = a;
		else 
			result = 8'bzzzz_zzzz;		
endmodule


////////~~~~~~~~END>  testb11.v

older/verilog_code/cpe300/hw4/correct/wave.vcd
$date
	Fri Sep 17 18:09:12 2021
$end
$version
	Icarus Verilog
$end
$timescale
	1ns
$end
$scope module testb11 $end
$var wire 8 ! sum [7:0] $end
$var wire 1 " displayRes $end
$var reg 1 # clk $end
$var reg 8 $ nIn [7:0] $end
$var reg 1 % restart $end
$var reg 1 & start $end
$var integer 32 ' i [31:0] $end
$scope module main $end
$var wire 1 # clk $end
$var wire 1 " done $end
$var wire 8 ( n [7:0] $end
$var wire 1 % restart $end
$var wire 1 & start $end
$var wire 1 ) nEqZero $end
$var wire 1 * WE $end
$var wire 2 + WA [1:0] $end
$var wire 8 , Sum [7:0] $end
$var wire 2 - SH [1:0] $end
$var wire 1 . RBE $end
$var wire 2 / RBA [1:0] $end
$var wire 1 0 RAE $end
$var wire 2 1 RAA [1:0] $end
$var wire 1 2 OE $end
$var wire 1 3 IE $end
$var wire 3 4 ALU [2:0] $end
$scope module control $end
$var wire 1 0 RAE $end
$var wire 1 . RBE $end
$var wire 1 * WE $end
$var wire 1 # clk $end
$var wire 1 5 restart $end
$var wire 1 6 start $end
$var wire 1 ) nEqZero $end
$var wire 2 7 WA [1:0] $end
$var wire 2 8 SH [1:0] $end
$var wire 2 9 RBA [1:0] $end
$var wire 2 : RAA [1:0] $end
$var wire 1 2 OE $end
$var wire 1 3 IE $end
$var wire 3 ; ALU [2:0] $end
$var reg 3 < nextstate [2:0] $end
$var reg 3 = state [2:0] $end
$upscope $end
$scope module datapath $end
$var wire 3 > ALU [2:0] $end
$var wire 1 3 IE $end
$var wire 1 2 OE $end
$var wire 2 ? RAA [1:0] $end
$var wire 1 0 RAE $end
$var wire 2 @ RBA [1:0] $end
$var wire 1 . RBE $end
$var wire 2 A SH [1:0] $end
$var wire 2 B WA [1:0] $end
$var wire 1 * WE $end
$var wire 1 # clk $end
$var wire 8 C nIn [7:0] $end
$var wire 8 D sum [7:0] $end
$var wire 8 E shOut [7:0] $end
$var wire 1 ) nEQZero $end
$var wire 8 F n [7:0] $end
$var wire 8 G aluOut [7:0] $end
$var wire 8 H RFb [7:0] $end
$var wire 8 I RFa [7:0] $end
$var reg 8 J rfIn [7:0] $end
$scope module RF $end
$var wire 8 K INPUT_D [7:0] $end
$var wire 2 L RAA [1:0] $end
$var wire 1 0 RAE $end
$var wire 2 M RBA [1:0] $end
$var wire 1 . RBE $end
$var wire 2 N WA [1:0] $end
$var wire 1 * WE $end
$var wire 1 # clk $end
$var wire 8 O ReadB [7:0] $end
$var wire 8 P ReadA [7:0] $end
$upscope $end
$scope module SHIFT $end
$var wire 2 Q sh [1:0] $end
$var wire 8 R a [7:0] $end
$var reg 8 S out [7:0] $end
$upscope $end
$scope module buffer1 $end
$var wire 8 T a [7:0] $end
$var wire 1 2 buf1 $end
$var reg 8 U result [7:0] $end
$upscope $end
$scope module muxs $end
$var wire 8 V a [7:0] $end
$var wire 8 W b [7:0] $end
$var wire 1 3 sel $end
$var reg 8 X result [7:0] $end
$upscope $end
$scope module theALU $end
$var wire 8 Y a [7:0] $end
$var wire 8 Z b [7:0] $end
$var wire 3 [ sel [2:0] $end
$var reg 8 \ out [7:0] $end
$upscope $end
$upscope $end
$upscope $end
$upscope $end
$enddefinitions $end
#0
$dumpvars
bx \
b101 [
bx Z
bx Y
bx X
b0 W
bx V
bz U
bx T
bx S
bx R
b0 Q
bx P
bx O
b0 N
b0 M
b0 L
b0 K
b0 J
bx I
bx H
bx G
bx F
bx E
bz D
b0 C
b0 B
b0 A
b0 @
b0 ?
b101 >
b0 =
b1 <
b101 ;
b0 :
b0 9
b0 8
b0 7
16
05
b101 4
03
02
b0 1
10
b0 /
1.
b0 -
bz ,
b0 +
1*
x)
b0 (
b0 '
0&
1%
b0 $
0#
0"
bz !
$end
#2
00
0.
b0 E
b0 S
b0 T
b0 V
b1 +
b1 7
b1 B
b1 N
b0 G
b0 R
b0 \
b100 <
1)
b0 F
b0 X
b0 4
b0 ;
b0 >
b0 [
b0 I
b0 P
b0 Y
b0 H
b0 O
b0 Z
13
b1 =
1#
#4
0#
#6
10
0*
b0 +
b0 7
b0 B
b0 N
b0 !
b0 ,
b0 D
b0 U
03
1"
12
b100 =
1#
#8
0#
#10
1#
#12
0#
#14
1#
#16
0#
#18
1#
#20
0#
#22
1#
#24
0#
#26
1#
#28
0#
#30
1#
#32
0#
#34
1#
#36
0#
#38
1#
#40
b1 $
b1 (
b1 C
b1 W
b0 <
15
0#
b1 '
0&
0%
#42
1.
1*
b1 <
b101 4
b101 ;
b101 >
b101 [
bz !
bz ,
bz D
bz U
0"
02
b0 =
1#
#44
0#
#46
00
0.
b1 J
b1 K
b1 +
b1 7
b1 B
b1 N
b10 <
0)
b1 F
b1 X
b0 4
b0 ;
b0 >
b0 [
13
b1 =
1#
#48
0#
#50
b1 E
b1 S
b1 T
b1 V
b1 G
b1 R
b1 \
b1 H
b1 O
b1 Z
10
1.
b100 4
b100 ;
b100 >
b100 [
b1 J
b1 K
b0 +
b0 7
b0 B
b0 N
b11 <
0)
b1 F
b1 X
03
b1 /
b1 9
b1 @
b1 M
b10 =
1#
#52
0#
#54
1)
b0 H
b0 O
b0 Z
b0 J
b0 K
0.
b0 F
b0 X
b1 +
b1 7
b1 B
b1 N
b0 E
b0 S
b0 T
b0 V
b100 <
b1 I
b1 P
b1 Y
b0 G
b0 R
b0 \
b1 1
b1 :
b1 ?
b1 L
b0 /
b0 9
b0 @
b0 M
b111 4
b111 ;
b111 >
b111 [
b11 =
1#
#56
0#
#58
b1 J
b1 K
0)
b1 F
b1 X
0*
b0 +
b0 7
b0 B
b0 N
b1 E
b1 S
b1 T
b1 V
b0 <
b1 G
b1 R
b1 \
b1 !
b1 ,
b1 D
b1 U
b0 1
b0 :
b0 ?
b0 L
b0 4
b0 ;
b0 >
b0 [
1"
12
b100 =
1#
#60
0#
#62
b0 J
b0 K
b1 H
b1 O
b1 Z
1)
b0 F
b0 X
1.
b0 E
b0 S
b0 T
b0 V
1*
b0 G
b0 R
b0 \
b1 <
b101 4
b101 ;
b101 >
b101 [
bz !
bz ,
bz D
bz U
0"
02
b0 =
1#
#64
0#
#66
00
0.
b1 J
b1 K
b1 +
b1 7
b1 B
b1 N
b10 <
0)
b1 F
b1 X
b0 4
b0 ;
b0 >
b0 [
b0 I
b0 P
b0 Y
b0 H
b0 O
b0 Z
13
b1 =
1#
#68
0#
#70
b1 E
b1 S
b1 T
b1 V
b1 G
b1 R
b1 \
b1 H
b1 O
b1 Z
10
1.
b100 4
b100 ;
b100 >
b100 [
b1 J
b1 K
b0 +
b0 7
b0 B
b0 N
b11 <
0)
b1 F
b1 X
03
b1 /
b1 9
b1 @
b1 M
b10 =
1#
#72
0#
#74
b0 H
b0 O
b0 Z
b0 J
b0 K
0.
1)
b0 F
b0 X
b1 +
b1 7
b1 B
b1 N
b0 E
b0 S
b0 T
b0 V
b100 <
b0 G
b0 R
b0 \
b1 I
b1 P
b1 Y
b1 1
b1 :
b1 ?
b1 L
b0 /
b0 9
b0 @
b0 M
b111 4
b111 ;
b111 >
b111 [
b11 =
1#
#76
0#
#78
b1 J
b1 K
0)
b1 F
b1 X
0*
b0 +
b0 7
b0 B
b0 N
b1 E
b1 S
b1 T
b1 V
b0 <
b1 G
b1 R
b1 \
b1 !
b1 ,
b1 D
b1 U
b0 1
b0 :
b0 ?
b0 L
b0 4
b0 ;
b0 >
b0 [
1"
12
b100 =
1#
#80
b10 $
b10 (
b10 C
b10 W
0#
b10 '
0&
0%
#82
b0 J
b0 K
b1 H
b1 O
b1 Z
1)
b0 F
b0 X
1.
b0 E
b0 S
b0 T
b0 V
1*
b0 G
b0 R
b0 \
b1 <
b101 4
b101 ;
b101 >
b101 [
bz !
bz ,
bz D
bz U
0"
02
b0 =
1#
#84
0#
#86
00
0.
b10 J
b10 K
b1 +
b1 7
b1 B
b1 N
b0 I
b0 P
b0 Y
b0 H
b0 O
b0 Z
b10 <
0)
b10 F
b10 X
b0 4
b0 ;
b0 >
b0 [
13
b1 =
1#
#88
0#
#90
b10 E
b10 S
b10 T
b10 V
b10 G
b10 R
b10 \
b10 H
b10 O
b10 Z
10
1.
b100 4
b100 ;
b100 >
b100 [
b10 J
b10 K
b0 +
b0 7
b0 B
b0 N
b11 <
0)
b10 F
b10 X
03
b1 /
b1 9
b1 @
b1 M
b10 =
1#
#92
0#
#94
b0 H
b0 O
b0 Z
b1 J
b1 K
0.
b1 F
b1 X
b1 +
b1 7
b1 B
b1 N
b1 E
b1 S
b1 T
b1 V
b10 <
b10 I
b10 P
b10 Y
b1 G
b1 R
b1 \
b1 1
b1 :
b1 ?
b1 L
b0 /
b0 9
b0 @
b0 M
b111 4
b111 ;
b111 >
b111 [
b11 =
1#
#96
0#
#98
b1 H
b1 O
b1 Z
b11 J
b11 K
1.
b11 F
b11 X
b0 +
b0 7
b0 B
b0 N
b11 E
b11 S
b11 T
b11 V
b11 <
b11 G
b11 R
b11 \
b0 1
b0 :
b0 ?
b0 L
b1 /
b1 9
b1 @
b1 M
b100 4
b100 ;
b100 >
b100 [
b10 =
1#
#100
0#
#102
1)
b0 J
b0 K
0.
b0 F
b0 X
b1 +
b1 7
b1 B
b1 N
b0 E
b0 S
b0 T
b0 V
b100 <
b1 I
b1 P
b1 Y
b0 H
b0 O
b0 Z
b0 G
b0 R
b0 \
b1 1
b1 :
b1 ?
b1 L
b0 /
b0 9
b0 @
b0 M
b111 4
b111 ;
b111 >
b111 [
b11 =
1#
#104
0#
#106
b11 J
b11 K
0)
b11 F
b11 X
0*
b0 +
b0 7
b0 B
b0 N
b11 E
b11 S
b11 T
b11 V
b0 <
b11 G
b11 R
b11 \
b11 !
b11 ,
b11 D
b11 U
b11 I
b11 P
b11 Y
b0 1
b0 :
b0 ?
b0 L
b0 4
b0 ;
b0 >
b0 [
1"
12
b100 =
1#
#108
0#
#110
b0 J
b0 K
b11 H
b11 O
b11 Z
1)
b0 F
b0 X
1.
b0 E
b0 S
b0 T
b0 V
1*
b0 G
b0 R
b0 \
b1 <
b101 4
b101 ;
b101 >
b101 [
bz !
bz ,
bz D
bz U
0"
02
b0 =
1#
#112
0#
#114
00
0.
b10 J
b10 K
b1 +
b1 7
b1 B
b1 N
b10 <
0)
b10 F
b10 X
b0 4
b0 ;
b0 >
b0 [
b0 I
b0 P
b0 Y
b0 H
b0 O
b0 Z
13
b1 =
1#
#116
0#
#118
b10 E
b10 S
b10 T
b10 V
b10 G
b10 R
b10 \
b10 H
b10 O
b10 Z
10
1.
b100 4
b100 ;
b100 >
b100 [
b10 J
b10 K
b0 +
b0 7
b0 B
b0 N
b11 <
0)
b10 F
b10 X
03
b1 /
b1 9
b1 @
b1 M
b10 =
1#
#120
05
0#
1%
#122
b0 H
b0 O
b0 Z
b1 J
b1 K
0.
b1 F
b1 X
b1 +
b1 7
b1 B
b1 N
b1 E
b1 S
b1 T
b1 V
b10 <
b1 G
b1 R
b1 \
b10 I
b10 P
b10 Y
b1 1
b1 :
b1 ?
b1 L
b0 /
b0 9
b0 @
b0 M
b111 4
b111 ;
b111 >
b111 [
b11 =
1#
#124
0#
#126
b1 H
b1 O
b1 Z
b11 J
b11 K
1.
b11 F
b11 X
b0 +
b0 7
b0 B
b0 N
b11 E
b11 S
b11 T
b11 V
b11 <
b11 G
b11 R
b11 \
b0 1
b0 :
b0 ?
b0 L
b1 /
b1 9
b1 @
b1 M
b100 4
b100 ;
b100 >
b100 [
b10 =
1#
#128
0#
#130
b0 J
b0 K
0.
1)
b0 F
b0 X
b1 +
b1 7
b1 B
b1 N
b0 E
b0 S
b0 T
b0 V
b100 <
b0 H
b0 O
b0 Z
b0 G
b0 R
b0 \
b1 I
b1 P
b1 Y
b1 1
b1 :
b1 ?
b1 L
b0 /
b0 9
b0 @
b0 M
b111 4
b111 ;
b111 >
b111 [
b11 =
1#
#132
0#
#134
b11 J
b11 K
0)
b11 F
b11 X
0*
b0 +
b0 7
b0 B
b0 N
b11 E
b11 S
b11 T
b11 V
b11 I
b11 P
b11 Y
b11 G
b11 R
b11 \
b11 !
b11 ,
b11 D
b11 U
b0 1
b0 :
b0 ?
b0 L
b0 4
b0 ;
b0 >
b0 [
1"
12
b100 =
1#
#135
b11 $
b11 (
b11 C
b11 W
b0 <
15
b11 '
0&
0%
#136
0#
#138
b0 J
b0 K
b11 H
b11 O
b11 Z
1)
b0 F
b0 X
1.
b0 E
b0 S
b0 T
b0 V
1*
b0 G
b0 R
b0 \
b1 <
b101 4
b101 ;
b101 >
b101 [
bz !
bz ,
bz D
bz U
0"
02
b0 =
1#
#140
0#
#142
00
0.
b11 J
b11 K
b1 +
b1 7
b1 B
b1 N
b0 I
b0 P
b0 Y
b0 H
b0 O
b0 Z
b10 <
0)
b11 F
b11 X
b0 4
b0 ;
b0 >
b0 [
13
b1 =
1#
#144
0#
#146
b11 E
b11 S
b11 T
b11 V
b11 G
b11 R
b11 \
b11 H
b11 O
b11 Z
10
1.
b100 4
b100 ;
b100 >
b100 [
b11 J
b11 K
b0 +
b0 7
b0 B
b0 N
b11 <
0)
b11 F
b11 X
03
b1 /
b1 9
b1 @
b1 M
b10 =
1#
#148
0#
#150
b0 H
b0 O
b0 Z
b10 J
b10 K
0.
b10 F
b10 X
b1 +
b1 7
b1 B
b1 N
b10 E
b10 S
b10 T
b10 V
b10 <
b11 I
b11 P
b11 Y
b10 G
b10 R
b10 \
b1 1
b1 :
b1 ?
b1 L
b0 /
b0 9
b0 @
b0 M
b111 4
b111 ;
b111 >
b111 [
b11 =
1#
#152
0#
#154
b10 H
b10 O
b10 Z
b101 J
b101 K
1.
b101 F
b101 X
b0 +
b0 7
b0 B
b0 N
b101 E
b101 S
b101 T
b101 V
b11 <
b101 G
b101 R
b101 \
b0 1
b0 :
b0 ?
b0 L
b1 /
b1 9
b1 @
b1 M
b100 4
b100 ;
b100 >
b100 [
b10 =
1#
#156
0#
#158
b1 J
b1 K
0.
b1 F
b1 X
b1 +
b1 7
b1 B
b1 N
b1 E
b1 S
b1 T
b1 V
b10 <
b10 I
b10 P
b10 Y
b0 H
b0 O
b0 Z
b1 G
b1 R
b1 \
b1 1
b1 :
b1 ?
b1 L
b0 /
b0 9
b0 @
b0 M
b111 4
b111 ;
b111 >
b111 [
b11 =
1#
#160
0#
#162
b1 H
b1 O
b1 Z
b110 J
b110 K
1.
b110 F
b110 X
b0 +
b0 7
b0 B
b0 N
b110 E
b110 S
b110 T
b110 V
b11 <
b110 G
b110 R
b110 \
b101 I
b101 P
b101 Y
b0 1
b0 :
b0 ?
b0 L
b1 /
b1 9
b1 @
b1 M
b100 4
b100 ;
b100 >
b100 [
b10 =
1#
#164
0#
#166
1)
b0 J
b0 K
0.
b0 F
b0 X
b1 +
b1 7
b1 B
b1 N
b0 E
b0 S
b0 T
b0 V
b100 <
b1 I
b1 P
b1 Y
b0 H
b0 O
b0 Z
b0 G
b0 R
b0 \
b1 1
b1 :
b1 ?
b1 L
b0 /
b0 9
b0 @
b0 M
b111 4
b111 ;
b111 >
b111 [
b11 =
1#
#168
0#
#170
b110 J
b110 K
0)
b110 F
b110 X
0*
b0 +
b0 7
b0 B
b0 N
b110 E
b110 S
b110 T
b110 V
b0 <
b110 G
b110 R
b110 \
b110 !
b110 ,
b110 D
b110 U
b110 I
b110 P
b110 Y
b0 1
b0 :
b0 ?
b0 L
b0 4
b0 ;
b0 >
b0 [
1"
12
b100 =
1#
#172
0#
#174
b0 J
b0 K
b110 H
b110 O
b110 Z
1)
b0 F
b0 X
1.
b0 E
b0 S
b0 T
b0 V
1*
b0 G
b0 R
b0 \
b1 <
b101 4
b101 ;
b101 >
b101 [
bz !
bz ,
bz D
bz U
0"
02
b0 =
1#
#175
05
1%
#176
0#
#178
00
0.
b11 J
b11 K
b1 +
b1 7
b1 B
b1 N
b10 <
0)
b11 F
b11 X
b0 4
b0 ;
b0 >
b0 [
b0 I
b0 P
b0 Y
b0 H
b0 O
b0 Z
13
b1 =
1#
#180
0#
#182
b11 E
b11 S
b11 T
b11 V
b11 G
b11 R
b11 \
b11 H
b11 O
b11 Z
10
1.
b100 4
b100 ;
b100 >
b100 [
b11 J
b11 K
b0 +
b0 7
b0 B
b0 N
b11 <
0)
b11 F
b11 X
03
b1 /
b1 9
b1 @
b1 M
b10 =
1#
#184
0#
#186
b0 H
b0 O
b0 Z
b10 J
b10 K
0.
b10 F
b10 X
b1 +
b1 7
b1 B
b1 N
b10 E
b10 S
b10 T
b10 V
b10 <
b10 G
b10 R
b10 \
b11 I
b11 P
b11 Y
b1 1
b1 :
b1 ?
b1 L
b0 /
b0 9
b0 @
b0 M
b111 4
b111 ;
b111 >
b111 [
b11 =
1#
#188
0#
#190
b10 H
b10 O
b10 Z
b101 J
b101 K
1.
b101 F
b101 X
b0 +
b0 7
b0 B
b0 N
b101 E
b101 S
b101 T
b101 V
b11 <
b101 G
b101 R
b101 \
b0 1
b0 :
b0 ?
b0 L
b1 /
b1 9
b1 @
b1 M
b100 4
b100 ;
b100 >
b100 [
b10 =
1#
#192
0#
#194
b1 J
b1 K
0.
b1 F
b1 X
b1 +
b1 7
b1 B
b1 N
b1 E
b1 S
b1 T
b1 V
b10 <
b0 H
b0 O
b0 Z
b1 G
b1 R
b1 \
b10 I
b10 P
b10 Y
b1 1
b1 :
b1 ?
b1 L
b0 /
b0 9
b0 @
b0 M
b111 4
b111 ;
b111 >
b111 [
b11 =
1#
#196
0#
#198
b1 H
b1 O
b1 Z
b110 J
b110 K
1.
b110 F
b110 X
b0 +
b0 7
b0 B
b0 N
b110 E
b110 S
b110 T
b110 V
b11 <
b101 I
b101 P
b101 Y
b110 G
b110 R
b110 \
b0 1
b0 :
b0 ?
b0 L
b1 /
b1 9
b1 @
b1 M
b100 4
b100 ;
b100 >
b100 [
b10 =
1#
#200
0#
#202
b0 J
b0 K
0.
1)
b0 F
b0 X
b1 +
b1 7
b1 B
b1 N
b0 E
b0 S
b0 T
b0 V
b100 <
b0 H
b0 O
b0 Z
b0 G
b0 R
b0 \
b1 I
b1 P
b1 Y
b1 1
b1 :
b1 ?
b1 L
b0 /
b0 9
b0 @
b0 M
b111 4
b111 ;
b111 >
b111 [
b11 =
1#
#204
0#
#206
b110 J
b110 K
0)
b110 F
b110 X
0*
b0 +
b0 7
b0 B
b0 N
b110 E
b110 S
b110 T
b110 V
b110 I
b110 P
b110 Y
b110 G
b110 R
b110 \
b110 !
b110 ,
b110 D
b110 U
b0 1
b0 :
b0 ?
b0 L
b0 4
b0 ;
b0 >
b0 [
1"
12
b100 =
1#
#208
0#
#210
b100 $
b100 (
b100 C
b100 W
b0 <
15
1#
b100 '
0&
0%
#212
0#
#214
b0 J
b0 K
b110 H
b110 O
b110 Z
1)
b0 F
b0 X
1.
b0 E
b0 S
b0 T
b0 V
1*
b0 G
b0 R
b0 \
b1 <
b101 4
b101 ;
b101 >
b101 [
bz !
bz ,
bz D
bz U
0"
02
b0 =
1#
#216
0#
#218
00
0.
b100 J
b100 K
b1 +
b1 7
b1 B
b1 N
b10 <
0)
b100 F
b100 X
b0 4
b0 ;
b0 >
b0 [
b0 I
b0 P
b0 Y
b0 H
b0 O
b0 Z
13
b1 =
1#
#220
0#
#222
b100 E
b100 S
b100 T
b100 V
b100 G
b100 R
b100 \
b100 H
b100 O
b100 Z
10
1.
b100 4
b100 ;
b100 >
b100 [
b100 J
b100 K
b0 +
b0 7
b0 B
b0 N
b11 <
0)
b100 F
b100 X
03
b1 /
b1 9
b1 @
b1 M
b10 =
1#
#224
0#
#226
b0 H
b0 O
b0 Z
b11 J
b11 K
0.
b11 F
b11 X
b1 +
b1 7
b1 B
b1 N
b11 E
b11 S
b11 T
b11 V
b10 <
b11 G
b11 R
b11 \
b100 I
b100 P
b100 Y
b1 1
b1 :
b1 ?
b1 L
b0 /
b0 9
b0 @
b0 M
b111 4
b111 ;
b111 >
b111 [
b11 =
1#
#228
0#
#230
b11 H
b11 O
b11 Z
b111 J
b111 K
1.
b111 F
b111 X
b0 +
b0 7
b0 B
b0 N
b111 E
b111 S
b111 T
b111 V
b11 <
b111 G
b111 R
b111 \
b0 1
b0 :
b0 ?
b0 L
b1 /
b1 9
b1 @
b1 M
b100 4
b100 ;
b100 >
b100 [
b10 =
1#
#232
0#
#234
b10 J
b10 K
0.
b10 F
b10 X
b1 +
b1 7
b1 B
b1 N
b10 E
b10 S
b10 T
b10 V
b10 <
b0 H
b0 O
b0 Z
b10 G
b10 R
b10 \
b11 I
b11 P
b11 Y
b1 1
b1 :
b1 ?
b1 L
b0 /
b0 9
b0 @
b0 M
b111 4
b111 ;
b111 >
b111 [
b11 =
1#
#236
0#
#238
b10 H
b10 O
b10 Z
b1001 J
b1001 K
1.
b1001 F
b1001 X
b0 +
b0 7
b0 B
b0 N
b1001 E
b1001 S
b1001 T
b1001 V
b11 <
b111 I
b111 P
b111 Y
b1001 G
b1001 R
b1001 \
b0 1
b0 :
b0 ?
b0 L
b1 /
b1 9
b1 @
b1 M
b100 4
b100 ;
b100 >
b100 [
b10 =
1#
#240
0#
#242
b1 J
b1 K
0.
b1 F
b1 X
b1 +
b1 7
b1 B
b1 N
b1 E
b1 S
b1 T
b1 V
b10 <
b0 H
b0 O
b0 Z
b1 G
b1 R
b1 \
b10 I
b10 P
b10 Y
b1 1
b1 :
b1 ?
b1 L
b0 /
b0 9
b0 @
b0 M
b111 4
b111 ;
b111 >
b111 [
b11 =
1#
#244
0#
#246
b1 H
b1 O
b1 Z
b1010 J
b1010 K
1.
b1010 F
b1010 X
b0 +
b0 7
b0 B
b0 N
b1010 E
b1010 S
b1010 T
b1010 V
b11 <
b1001 I
b1001 P
b1001 Y
b1010 G
b1010 R
b1010 \
b0 1
b0 :
b0 ?
b0 L
b1 /
b1 9
b1 @
b1 M
b100 4
b100 ;
b100 >
b100 [
b10 =
1#
#248
0#
#250
b0 J
b0 K
0.
1)
b0 F
b0 X
b1 +
b1 7
b1 B
b1 N
b0 E
b0 S
b0 T
b0 V
b100 <
b0 H
b0 O
b0 Z
b0 G
b0 R
b0 \
b1 I
b1 P
b1 Y
b1 1
b1 :
b1 ?
b1 L
b0 /
b0 9
b0 @
b0 M
b111 4
b111 ;
b111 >
b111 [
b11 =
05
1#
1%
#252
0#
#254
b1010 J
b1010 K
0)
b1010 F
b1010 X
0*
b0 +
b0 7
b0 B
b0 N
b1010 E
b1010 S
b1010 T
b1010 V
b1010 I
b1010 P
b1010 Y
b1010 G
b1010 R
b1010 \
b1010 !
b1010 ,
b1010 D
b1010 U
b0 1
b0 :
b0 ?
b0 L
b0 4
b0 ;
b0 >
b0 [
1"
12
b100 =
1#
#255
b101 $
b101 (
b101 C
b101 W
b0 <
15
b101 '
0&
0%
#256
0#
#258
b0 J
b0 K
b1010 H
b1010 O
b1010 Z
1)
b0 F
b0 X
1.
b0 E
b0 S
b0 T
b0 V
1*
b0 G
b0 R
b0 \
b1 <
b101 4
b101 ;
b101 >
b101 [
bz !
bz ,
bz D
bz U
0"
02
b0 =
1#
#260
0#
