verilog_code/cpe300/hw1/barrel8_right/sub_mod/barrel8.v
/*
    the 8-bit barrel-right shift/bypass

        BYPASS:  selector == 0
        RIGHT SHIFT:  selector == 1
*/

module barrel8 (out_y, selector, in_x);
    output reg [7:0] out_y;
    input wire selector;
    input wire [7:0] in_x;

    always @ (in_x) begin
        out_y = in_x;
        if (selector) begin
            out_y = out_y >> 1;
        end
    end

endmodule

////////~~~~~~~~END>  barrel8_right.v

verilog_code/cpe300/hw1/barrel8_right/sub_mod/barrel8_TB.v
/*
	test "barrel8"
*/

`timescale 1ns/1ns

`include "barrel8.v"

`define BITZ 8
`define STEP 5


module barrel8_TB ();
	wire [`BITZ-1:0] outY;
	reg SEL;
	reg [`BITZ-1:0] inpX;
	integer idx;

	barrel8 DUT (
					.out_y(outY),
					.selector(SEL),
					.in_x(inpX)
				);
	
	initial begin
		$dumpfile("barrel8_TB.vcd");
		$dumpvars(0, barrel8_TB);
		SEL = 1'b0;
		inpX = 8'b11111111;
		$display("\nTIME  selector    input         output     ACTION\n");

		for (idx = 0; idx < `BITZ; idx++) begin
			# `STEP
			$display("%3t       %b      %b      %b    BYPASS", 
				$time, SEL, inpX, outY);
			inpX = inpX >> 1;
		end

		$display("");
		inpX = 8'b11111111;
		SEL = 1'b1;
		for (idx = 0; idx < `BITZ; idx++) begin
			# `STEP
			$display("%3t       %b      %b      %b    RIGHT SHIFT", 
				$time, SEL, inpX, outY);
			inpX = inpX >> 1;
		end
		
		# `STEP
		$display("\n\n\t~ ~ ~ TEST COMPLETE ~ ~ ~\n\n");
		$finish;
	end

endmodule

////////~~~~~~~~END>  barrel8_TB.v

verilog_code/cpe300/hw1/barrel8_right/sub_mod/barrel8_TB.vcd
$date
	Mon Aug 30 22:57:53 2021
$end
$version
	Icarus Verilog
$end
$timescale
	1ns
$end
$scope module barrel8_TB $end
$var wire 8 ! outY [7:0] $end
$var reg 1 " SEL $end
$var reg 8 # inpX [7:0] $end
$var integer 32 $ idx [31:0] $end
$scope module DUT $end
$var wire 8 % in_x [7:0] $end
$var wire 1 " selector $end
$var reg 8 & out_y [7:0] $end
$upscope $end
$upscope $end
$enddefinitions $end
#0
$dumpvars
b11111111 &
b11111111 %
b0 $
b11111111 #
0"
b11111111 !
$end
#5
b1111111 !
b1111111 &
b1 $
b1111111 #
b1111111 %
#10
b111111 !
b111111 &
b10 $
b111111 #
b111111 %
#15
b11111 !
b11111 &
b11 $
b11111 #
b11111 %
#20
b1111 !
b1111 &
b100 $
b1111 #
b1111 %
#25
b111 !
b111 &
b101 $
b111 #
b111 %
#30
b11 !
b11 &
b110 $
b11 #
b11 %
#35
b1 !
b1 &
b111 $
b1 #
b1 %
#40
b1111111 !
b1111111 &
1"
b0 $
b11111111 #
b11111111 %
#45
b111111 !
b111111 &
b1 $
b1111111 #
b1111111 %
#50
b11111 !
b11111 &
b10 $
b111111 #
b111111 %
#55
b1111 !
b1111 &
b11 $
b11111 #
b11111 %
#60
b111 !
b111 &
b100 $
b1111 #
b1111 %
#65
b11 !
b11 &
b101 $
b111 #
b111 %
#70
b1 !
b1 &
b110 $
b11 #
b11 %
#75
b0 !
b0 &
b111 $
b1 #
b1 %
#80
b1000 $
b0 #
b0 %
