older/verilog_code/cpe300/lab7_code/proof/summing.v
/*
	a combined GDP, all modules
    proof of the summing algorithm
*/

`timescale 1ns/1ns 
`define HALF 5
`define START 0   
`define STOP 22   // don't do more than 22
`define DEBUG_TB -999
`define DEBUG_WAVE -888
//`define DEBUG_CU -777
//`define DEBUG_DP -666


module tb();
	wire [7:0] result;
	wire done;
	reg [7:0] n_input;
	reg start;
    reg reset;
    reg clock;

	integer idx;
    real check;
    time past;
    time split;

    general_data_path GDP (
                            .result(result),
                            .done(done),
                            .n_input(n_input),
                            .start(start), 
                            .reset(reset), 
                            .clock(clock)
                        );

	always begin
		#`HALF;
		clock = ~clock;
	end
	
	initial begin
        `ifdef DEBUG_WAVE
		    $dumpfile("wave.vcd");
            $dumpvars(0, tb);
        `endif
		$write("\n testing the summing algorithm  ,  N [ %3d : %3d ]  on %1d ns cycles\n\n",
            `START, `STOP, 2 * `HALF);
        $write("    input  \"N\"      |        sum of N       |  expected        time ns   split\n");
        $write(" --------------------------------------------------------\n");
        past = 0;
        split = 0;

		start = 1'b1;
		reset = 1'b0;
		clock = 1'b0;

        for (idx = `START; idx <= `STOP; idx = idx + 1) begin
            past = $time;
            reset = 1'b0;
            n_input = idx;
            check = idx * (idx + 1) / 2;

            while (done != 1'b1) begin
                #(`HALF + `HALF);
            end

            split = $time - past;

            `ifdef DEBUG_TB
                $write("  {%3d}  %4b_%4b  |  %4b_%4b  -->  %3d  |      %3d",
                    n_input, n_input[7:4], n_input[3:0], 
                    result[7:4], result[3:0], result, check);
                if(result == check) begin
                    $write("  |     %6t    %4t        CORRECT  \n", $time, split);
                end
                else begin
                    $write("  !!!* WRONG *!!!\n");
                end
            `endif
            
            reset = 1'b1;
            #(`HALF + `HALF);
        end

        #3;
        $write("\n\n\t\t ~ ~ ~ TEST COMPLETE ~ ~ ~  %7t  ns\n\n", $time);
		$finish;
	end
endmodule


////~~~~ top entity, combines control unit and data path
module general_data_path (
                            output wire [7:0] result,
                            output wire done,
                            input wire [7:0] n_input,
                            input wire start, 
                            input wire reset, 
                            input wire clock
                        );	
	wire IE;
    wire WE;
    wire [1:0] WA;
    wire RAE;
    wire [1:0] RAA;
    wire RBE;
    wire [1:0] RBA;
    wire [2:0] ALU;
    wire [1:0] SH;
    wire OE;
    wire n_is_0; 
	
    assign done = OE;

    control_unit CU (
                        .IE(IE), 
                        .WE(WE),
                        .WA(WA),
                        .RAE(RAE),
                        .RAA(RAA),
                        .RBE(RBE),
                        .RBA(RBA),
                        .ALU(ALU),
                        .SH(SH),
                        .OE(OE),
                        .n_is_0(n_is_0),
                        .start(start),
                        .reset(reset),
                        .clock(clock)
                    );

    data_path DP (
                    .n_is_0(n_is_0),
                    .result(result),
                    .n_input(n_input),
                    .IE(IE),
                    .WE(WE),
                    .WA(WA),
                    .RAE(RAE),
                    .RAA(RAA),
                    .RBE(RBE),
                    .RBA(RBA),
                    .ALU(ALU),
                    .SH(SH),
                    .OE(OE),
                    .clock(clock)
                );
endmodule


////~~~~ control unit applied to data path
module control_unit (
                        output wire IE, 
                        output wire WE,
                        output wire [1:0] WA,
                        output wire RAE,
                        output wire [1:0] RAA,
                        output wire RBE,
                        output wire [1:0] RBA,
                        output wire [2:0] ALU,
                        output wire [1:0] SH,
                        output wire OE,
                        input wire n_is_0,
                        input wire start,
                        input wire reset,
                        input wire clock
                    );

	reg [2:0] state;
	reg [2:0] n_state;

	parameter s0 = 3'b000;
	parameter s1 = 3'b001;
	parameter s2 = 3'b010;
	parameter s3 = 3'b011;
	parameter s4 = 3'b100;
	
	initial begin
        state = s0;
    end
	
	always @ (posedge clock) begin
        if (reset == 1'b1) n_state = s0;  // interupt all
        `ifdef DEBUG_CU
            $write("\n st   nst  || IE | WE | WA | RAE | RAA | RBE | RBA | ALU | SH | OE || start | reset | n==0    %7t ns\n",
                $time);
            $write("-------------------------------------------------------------------------------------------\n");
            $write(" %3b  %3b  || %1b  | %1b  | %2b |  %1b  | %2b  |  %1b  | %2b  | %3b | %2b | %1b  ||   %1b   |   %1b   |  %1b\n", 
                    state, n_state, IE,    WE,    WA,  RAE,    RAA,    RBE,   RBA,   ALU,   SH,   OE,   start, reset,   n_is_0);
        `endif
        state <= n_state;
    end

    always @ (*) begin
        case(state)
            s0 : n_state = (start) ? s1 : s0;     // rf[00] <-- 0  make zero  ,  wait for start
            s1 : n_state = (n_is_0) ? s4 : s2;    // rf[01] <-- N  ,  get input
            s2 : n_state = s3;                    // rf[00] <-- rf[00] + 1  ,  increment sum
            s3 : n_state = (n_is_0) ? s4 : s2;    // rf[01] <-- rf[01] - 1  ,  decrement N
            s4 : n_state = (reset) ? s0 : s4;     // show rf[00]  ,  output and wait for reset
            default : n_state = s0;               // stop the latch
        endcase
	end
	
	assign IE = (state == s1);
		
	assign WE = (state == s0) || 
                (state == s1) || 
                (state == s2) || 
                (state == s3);
                
	assign WA[1] = 1'b0;
	assign WA[0] = (state == s1) || 
                   (state == s3);
		
	assign RAE = (state == s0) || 
                 (state == s2) || 
                 (state == s3) || 
                 (state == s4);
	assign RAA[1] = 1'b0;
	assign RAA[0] = (state == s3);
		
	assign RBE = (state == s0) ||
                 (state == s2);
	assign RBA[1] = 1'b0;
	assign RBA[0] = (state == s2);
		
	assign ALU[2] = (state == s0) || 
                    (state == s2) || 
                    (state == s3);
	assign ALU[1] = (state == s3);
	assign ALU[0] = (state == s0) ||
                    (state == s3);
		
	assign SH[1] = 1'b0;
	assign SH[0] = 1'b0;
	assign OE = (state == s4);	
endmodule


////~~~~ data path combining the 5 components 
module data_path (
                    output wire n_is_0,
                    output wire [7:0] result,
                    input wire [7:0] n_input,
                    input wire IE,
                    input wire WE,
                    input wire [1:0] WA,
                    input wire RAE,
                    input wire [1:0] RAA,
                    input wire RBE,
                    input wire [1:0] RBA,
                    input wire [2:0] ALU,
                    input wire [1:0] SH,
                    input wire OE,
                    input wire clock
                );

    parameter BLANK = 8'b0000_0000;  
    wire [7:0] from_mux;          
	reg [7:0] to_register_file;
    wire [7:0] rf_port_A;
    wire [7:0] rf_port_B;
    wire [7:0] from_alu;
    wire [7:0] from_shifter;
	
    /*
        This internal register completes the feedback.
        Unlike the other connections, it must be a register.
        It is very important and provides the initialization,
        along with proper transfer sequence.
        To use a wire, all subordinate modules would need to be structural.
    */
    initial begin
        to_register_file = BLANK;
    end
    always @ (*) begin
        to_register_file = from_mux;
    end
	
    /*
        This is the probe right under the MUX.
        It won't fail if you move states correctly.
        Don't get too crazy with the logic checks.
    */
	assign n_is_0 = (from_mux == 8'b0000_0000); 

    c1_mux comp1 (
                    .from_mux(from_mux),
                    .new_data(n_input), 
                    .feedback(from_shifter),
                    .IE(IE)
                );

    c2_register_file comp2 (
                            .port_A(rf_port_A),
                            .port_B(rf_port_B),     
                            .from_mux(to_register_file),
                            .WE(WE),                
                            .WA(WA),          
                            .RAE(RAE),    
                            .RAA(RAA),         
                            .RBE(RBE),            
                            .RBA(RBA),      
                            .clock(clock)
                        ); 

    c3_alu comp3 (
                    .from_alu(from_alu),
                    .A_bus(rf_port_A),
                    .B_bus(rf_port_B),
                    .ALU(ALU)
                );

    c4_shifter comp4 (
                        .from_shifter(from_shifter),
                        .from_alu(from_alu),
                        .SH(SH)
                    );


    c5_triBuff comp5 (
                        .result(result), 
                        .from_shifter(from_shifter), 
                        .OE(OE)
                    );
    
    `ifdef DEBUG_DP
        always @ (posedge clock) begin
            #1;
            $write("\n ************************************************\n");
            $write(" {data_path}                               %7t ns\n", $time);
            $write("               n_is_0:  %1b\n", n_is_0);
            $write(" -------------------------\n");
            $write("                   IE:  %1b\n", IE);
            $write("  mux[0], shifter_out:  %4b_%4b\n", from_shifter[7:4], from_shifter[3:0]);
            $write("         mux[1], n_in:  %4b_%4b\n", n_input[7:4], n_input[3:0]);
            $write("         mux out, nnn:  %4b_%4b\n", from_mux[7:4], from_mux[3:0]);
            $write(" ---------------------------------\n");
            $write("               rf_inp:  %4b_%4b\n", to_register_file[7:4], to_register_file[3:0]);
            $write(" WE:   %1b  ,  WA:   %2b\n", WE, WA);
            $write(" RAE:  %1b  ,  RAA:  %2b\n", RAE, RAA);
            $write(" RBE:  %1b  ,  RBA:  %2b\n", RBE, RBA);
            $write(" reg[00]:  %4b_%4b \"k\"\n", comp2.internal[2'b00][7:4], comp2.internal[2'b00][3:0]);
            $write(" reg[01]:  %4b_%4b \"N\"\n"  , comp2.internal[2'b01][7:4], comp2.internal[2'b01][3:0]);
            $write(" reg[10]:  %4b_%4b\n"        , comp2.internal[2'b10][7:4], comp2.internal[2'b10][3:0]);
            $write(" reg[11]:  %4b_%4b\n"        , comp2.internal[2'b11][7:4], comp2.internal[2'b11][3:0]);
            $write("               port A:  %4b_%4b\n", rf_port_A[7:4], rf_port_A[3:0]);
            $write("               port B:  %4b_%4b\n", rf_port_B[7:4], rf_port_B[3:0]);
            $write(" --------------------------------------\n");
            $write("        alu operation:  %3b\n", ALU);
            $write("           alu output:  %4b_%4b\n", from_alu[7:4], from_alu[3:0]);
            $write(" ---------------------------------\n");
            $write("    shifter operation:  %3b\n", SH);
            $write("       shifter output:  %4b_%4b\n", from_shifter[7:4], from_shifter[3:0]);
            $write(" ---------------------------------\n");
            $write("                   OE:  %1b\n", OE);
            $write("               result:  %4b_%4b", result[7:4], result[3:0]);
            if (OE == 1'b1) $write("   !!!SUCCESS!!!\n");
            else $write("      ...working\n");
            $write(" ************************************************\n");
        end
    `endif
endmodule


////~~~~ 2-to-1 mux, 8 bits, component 1 of 5
module c1_mux (
                    output reg [7:0] from_mux,
                    input wire [7:0] new_data, 
                    input wire [7:0] feedback,
                    input wire IE
                );
	
	always @ (*) begin
        from_mux = (IE == 1'b1) ? new_data : feedback;
    end
endmodule


////~~~~ register file, component 2 of 5
module c2_register_file(
                            output wire [7:0] port_A,     // value assigned to port A
                            output wire [7:0] port_B,     // value assigned to port B
                            input wire [7:0] from_mux,    // bus after MUX selection
                            input wire WE,                // write enable
                            input wire [1:0] WA,          // write address
                            input wire RAE,               // port A read enable
                            input wire [1:0] RAA,         // port A Read address 
                            input wire RBE,               // port B read enable
                            input wire [1:0] RBA,         // port B read address
                            input wire clock
                        ); 
	
    parameter BLANK = 8'b0000_0000;

    // x4 8-bit registers "4x8", index them in binary
	reg [7:0] internal [3:0]; 

    // only write if WE is active
	always @ (posedge clock) begin
        if (WE == 1'b1) internal[WA] <= from_mux;
    end
     
    // reading to ports is done in combination, if enabled
    assign port_A = (RAE == 1'b1) ? internal[RAA] : BLANK; 
    assign port_B = (RBE == 1'b1) ? internal[RBA] : BLANK;
endmodule


////~~~~ ALU, component 3 of 5
module c3_alu (
                output reg [7:0] from_alu,
                input wire [7:0] A_bus,
                input wire [7:0] B_bus,
                input wire [2:0] ALU
            );

    parameter pass_A = 3'b000;     // bus A passes through
    parameter A_and_B = 3'b001;    // bitwise AND, A & B
    parameter A_or_B = 3'b010;     // bitwise OR, A | B
    parameter not_A = 3'b011;      // bitwise negate, ~A
    parameter A_add_B = 3'b100;    // addition, A + B
    parameter A_sub_B = 3'b101;    // subtraction, A - B
    parameter inc_A = 3'b110;      // increment, A = A + 1
    parameter dec_A = 3'b111;      // decrement, A = A - 1

    always @ (*) begin 
        case(ALU) 
            pass_A  : from_alu = A_bus;                  
            A_and_B : from_alu = A_bus & B_bus;                  
            A_or_B  : from_alu = A_bus | B_bus; 
            not_A   : from_alu = ~A_bus;
            A_add_B : from_alu = A_bus + B_bus;
            A_sub_B : from_alu = A_bus - B_bus;
            inc_A   : from_alu = A_bus + 1'b1;
            dec_A   : from_alu = A_bus - 1'b1;                
        endcase
    end
endmodule


////~~~~ shifter, componenet 4 of 5
module c4_shifter (
                    output reg [7:0] from_shifter,
                    input wire [7:0] from_alu,
                    input wire [1:0] SH
                );

    parameter PASS = 2'b00;      // pass through
    parameter LEFT = 2'b01;      // left shift and fill with 0's
    parameter RIGHT = 2'b10;     // right shift and fill with 0's
    parameter ROTATE = 2'b11;    // rotate right

    always @ (*) begin 
        case(SH) 
            PASS   : from_shifter = from_alu;                  
            LEFT   : from_shifter = from_alu << 1;                 
            RIGHT  : from_shifter = from_alu >> 1;
            ROTATE : from_shifter = {from_alu[6:0], from_alu[7]};                    
        endcase
    end
endmodule


////~~~~ final output buffer, componenet 5 of 5
module c5_triBuff (
                    output reg [7:0] result, 
                    input wire [7:0] from_shifter, 
                    input wire OE
                );

	always @ (*) begin
        result = (OE == 1'b1) ? from_shifter : 8'bzzzz_zzzz;
    end		
endmodule


////////~~~~~~~~END>  summing.v

older/verilog_code/cpe300/lab7_code/proof/wave.vcd
$date
	Tue Oct 19 12:47:46 2021
$end
$version
	Icarus Verilog
$end
$timescale
	1ns
$end
$scope module tb $end
$var wire 8 ! result [7:0] $end
$var wire 1 " done $end
$var reg 1 # clock $end
$var reg 8 $ n_input [7:0] $end
$var reg 64 % past [63:0] $end
$var reg 1 & reset $end
$var reg 64 ' split [63:0] $end
$var reg 1 ( start $end
$var real 1 ) check $end
$var integer 32 * idx [31:0] $end
$scope module GDP $end
$var wire 1 # clock $end
$var wire 1 " done $end
$var wire 8 + n_input [7:0] $end
$var wire 1 & reset $end
$var wire 1 ( start $end
$var wire 8 , result [7:0] $end
$var wire 1 - n_is_0 $end
$var wire 1 . WE $end
$var wire 2 / WA [1:0] $end
$var wire 2 0 SH [1:0] $end
$var wire 1 1 RBE $end
$var wire 2 2 RBA [1:0] $end
$var wire 1 3 RAE $end
$var wire 2 4 RAA [1:0] $end
$var wire 1 5 OE $end
$var wire 1 6 IE $end
$var wire 3 7 ALU [2:0] $end
$scope module CU $end
$var wire 1 3 RAE $end
$var wire 1 1 RBE $end
$var wire 1 . WE $end
$var wire 1 # clock $end
$var wire 1 & reset $end
$var wire 1 ( start $end
$var wire 1 - n_is_0 $end
$var wire 2 8 WA [1:0] $end
$var wire 2 9 SH [1:0] $end
$var wire 2 : RBA [1:0] $end
$var wire 2 ; RAA [1:0] $end
$var wire 1 5 OE $end
$var wire 1 6 IE $end
$var wire 3 < ALU [2:0] $end
$var reg 3 = n_state [2:0] $end
$var reg 3 > state [2:0] $end
$upscope $end
$scope module DP $end
$var wire 3 ? ALU [2:0] $end
$var wire 1 6 IE $end
$var wire 1 5 OE $end
$var wire 2 @ RAA [1:0] $end
$var wire 1 3 RAE $end
$var wire 2 A RBA [1:0] $end
$var wire 1 1 RBE $end
$var wire 2 B SH [1:0] $end
$var wire 2 C WA [1:0] $end
$var wire 1 . WE $end
$var wire 1 # clock $end
$var wire 8 D n_input [7:0] $end
$var wire 8 E rf_port_B [7:0] $end
$var wire 8 F rf_port_A [7:0] $end
$var wire 8 G result [7:0] $end
$var wire 1 - n_is_0 $end
$var wire 8 H from_shifter [7:0] $end
$var wire 8 I from_mux [7:0] $end
$var wire 8 J from_alu [7:0] $end
$var reg 8 K to_register_file [7:0] $end
$scope module comp1 $end
$var wire 1 6 IE $end
$var wire 8 L new_data [7:0] $end
$var wire 8 M feedback [7:0] $end
$var reg 8 N from_mux [7:0] $end
$upscope $end
$scope module comp2 $end
$var wire 2 O RAA [1:0] $end
$var wire 1 3 RAE $end
$var wire 2 P RBA [1:0] $end
$var wire 1 1 RBE $end
$var wire 2 Q WA [1:0] $end
$var wire 1 . WE $end
$var wire 1 # clock $end
$var wire 8 R from_mux [7:0] $end
$var wire 8 S port_B [7:0] $end
$var wire 8 T port_A [7:0] $end
$upscope $end
$scope module comp3 $end
$var wire 3 U ALU [2:0] $end
$var wire 8 V A_bus [7:0] $end
$var wire 8 W B_bus [7:0] $end
$var reg 8 X from_alu [7:0] $end
$upscope $end
$scope module comp4 $end
$var wire 2 Y SH [1:0] $end
$var wire 8 Z from_alu [7:0] $end
$var reg 8 [ from_shifter [7:0] $end
$upscope $end
$scope module comp5 $end
$var wire 1 5 OE $end
$var wire 8 \ from_shifter [7:0] $end
$var reg 8 ] result [7:0] $end
$upscope $end
$upscope $end
$upscope $end
$upscope $end
$enddefinitions $end
#0
$dumpvars
bz ]
bx \
bx [
bx Z
b0 Y
bx X
bx W
bx V
b101 U
bx T
bx S
b0 R
b0 Q
b0 P
b0 O
bx N
bx M
b0 L
b0 K
bx J
bx I
bx H
bz G
bx F
bx E
b0 D
b0 C
b0 B
b0 A
b0 @
b101 ?
b0 >
b1 =
b101 <
b0 ;
b0 :
b0 9
b0 8
b101 7
06
05
b0 4
13
b0 2
11
b0 0
b0 /
1.
x-
bz ,
b0 +
b0 *
r0 )
1(
b0 '
0&
b0 %
b0 $
0#
0"
bz !
$end
#5
03
b0 H
b0 M
b0 [
b0 \
b0 J
b0 X
b0 Z
b100 =
1-
b0 I
b0 N
b1 /
b1 8
b1 C
b1 Q
01
b0 7
b0 <
b0 ?
b0 U
b0 F
b0 T
b0 V
b0 E
b0 S
b0 W
16
b1 >
1#
#10
0#
#15
0.
b0 /
b0 8
b0 C
b0 Q
13
b0 !
b0 ,
b0 G
b0 ]
06
1"
15
b100 >
1#
#20
b0 =
0#
1&
b10100 '
#25
1.
b1 =
13
11
b101 7
b101 <
b101 ?
b101 U
bz !
bz ,
bz G
bz ]
0"
05
b0 >
1#
#30
0#
r1 )
b1 $
b1 +
b1 D
b1 L
0&
b11110 %
b1 *
#35
03
b1 K
b1 R
b10 =
0-
b1 I
b1 N
b1 /
b1 8
b1 C
b1 Q
01
b0 7
b0 <
b0 ?
b0 U
16
b1 >
1#
#40
0#
#45
b1 H
b1 M
b1 [
b1 \
b1 J
b1 X
b1 Z
13
b1 E
b1 S
b1 W
b1 K
b1 R
b100 7
b100 <
b100 ?
b100 U
b11 =
0-
b1 I
b1 N
b0 /
b0 8
b0 C
b0 Q
11
06
b1 2
b1 :
b1 A
b1 P
b10 >
1#
#50
0#
#55
1-
b0 K
b0 R
b0 E
b0 S
b0 W
b0 I
b0 N
b0 H
b0 M
b0 [
b0 \
b100 =
b1 /
b1 8
b1 C
b1 Q
b1 F
b1 T
b1 V
01
b0 J
b0 X
b0 Z
b1 4
b1 ;
b1 @
b1 O
b0 2
b0 :
b0 A
b0 P
b111 7
b111 <
b111 ?
b111 U
b11 >
1#
#60
0#
#65
b1 K
b1 R
0-
b1 I
b1 N
b1 H
b1 M
b1 [
b1 \
0.
b0 /
b0 8
b0 C
b0 Q
b1 J
b1 X
b1 Z
b1 !
b1 ,
b1 G
b1 ]
b0 4
b0 ;
b0 @
b0 O
b0 7
b0 <
b0 ?
b0 U
1"
15
b100 >
1#
#70
b0 =
0#
1&
b101000 '
#75
b0 K
b0 R
1-
b0 I
b0 N
1.
b1 F
b1 T
b1 V
b1 E
b1 S
b1 W
b0 H
b0 M
b0 [
b0 \
b0 J
b0 X
b0 Z
b1 =
13
11
b101 7
b101 <
b101 ?
b101 U
bz !
bz ,
bz G
bz ]
0"
05
b0 >
1#
#80
0#
r3 )
b10 $
b10 +
b10 D
b10 L
0&
b1010000 %
b10 *
#85
03
b10 K
b10 R
b10 =
0-
b10 I
b10 N
b1 /
b1 8
b1 C
b1 Q
01
b0 7
b0 <
b0 ?
b0 U
b0 F
b0 T
b0 V
b0 E
b0 S
b0 W
16
b1 >
1#
#90
0#
#95
b10 H
b10 M
b10 [
b10 \
b10 J
b10 X
b10 Z
13
b10 E
b10 S
b10 W
b10 K
b10 R
b100 7
b100 <
b100 ?
b100 U
b11 =
0-
b10 I
b10 N
b0 /
b0 8
b0 C
b0 Q
11
06
b1 2
b1 :
b1 A
b1 P
b10 >
1#
#100
0#
#105
b1 K
b1 R
b0 E
b0 S
b0 W
b1 I
b1 N
b1 H
b1 M
b1 [
b1 \
b10 =
b1 /
b1 8
b1 C
b1 Q
01
b1 J
b1 X
b1 Z
b10 F
b10 T
b10 V
b1 4
b1 ;
b1 @
b1 O
b0 2
b0 :
b0 A
b0 P
b111 7
b111 <
b111 ?
b111 U
b11 >
1#
#110
0#
#115
b10 F
b10 T
b10 V
b11 K
b11 R
b1 E
b1 S
b1 W
b11 I
b11 N
13
b11 H
b11 M
b11 [
b11 \
b11 =
1.
b0 /
b0 8
b0 C
b0 Q
11
b11 J
b11 X
b11 Z
b0 4
b0 ;
b0 @
b0 O
b1 2
b1 :
b1 A
b1 P
b100 7
b100 <
b100 ?
b100 U
b10 >
1#
#120
0#
#125
b0 K
b0 R
1-
b0 I
b0 N
b0 H
b0 M
b0 [
b0 \
b100 =
b1 /
b1 8
b1 C
b1 Q
01
b0 E
b0 S
b0 W
b0 J
b0 X
b0 Z
b1 F
b1 T
b1 V
b1 4
b1 ;
b1 @
b1 O
b0 2
b0 :
b0 A
b0 P
b111 7
b111 <
b111 ?
b111 U
b11 >
1#
#130
0#
#135
b11 K
b11 R
0-
b11 I
b11 N
b11 H
b11 M
b11 [
b11 \
0.
b0 /
b0 8
b0 C
b0 Q
b11 F
b11 T
b11 V
b11 J
b11 X
b11 Z
b11 !
b11 ,
b11 G
b11 ]
b0 4
b0 ;
b0 @
b0 O
b0 7
b0 <
b0 ?
b0 U
1"
15
b100 >
1#
#140
b0 =
0#
1&
b111100 '
#145
b0 K
b0 R
1-
b0 I
b0 N
1.
b11 F
b11 T
b11 V
b11 E
b11 S
b11 W
b0 H
b0 M
b0 [
b0 \
b0 J
b0 X
b0 Z
b1 =
13
11
b101 7
b101 <
b101 ?
b101 U
bz !
bz ,
bz G
bz ]
0"
05
b0 >
1#
#150
0#
r6 )
b11 $
b11 +
b11 D
b11 L
0&
b10010110 %
b11 *
#155
03
b11 K
b11 R
b0 F
b0 T
b0 V
b0 E
b0 S
b0 W
b10 =
0-
b11 I
b11 N
b1 /
b1 8
b1 C
b1 Q
01
b0 7
b0 <
b0 ?
b0 U
16
b1 >
1#
#160
0#
#165
b11 H
b11 M
b11 [
b11 \
b11 J
b11 X
b11 Z
13
b11 E
b11 S
b11 W
b11 K
b11 R
b100 7
b100 <
b100 ?
b100 U
b11 =
0-
b11 I
b11 N
b0 /
b0 8
b0 C
b0 Q
11
06
b1 2
b1 :
b1 A
b1 P
b10 >
1#
#170
0#
#175
b10 K
b10 R
b0 E
b0 S
b0 W
b10 I
b10 N
b10 H
b10 M
b10 [
b10 \
b10 =
b1 /
b1 8
b1 C
b1 Q
b11 F
b11 T
b11 V
01
b10 J
b10 X
b10 Z
b1 4
b1 ;
b1 @
b1 O
b0 2
b0 :
b0 A
b0 P
b111 7
b111 <
b111 ?
b111 U
b11 >
1#
#180
0#
#185
b11 F
b11 T
b11 V
b101 K
b101 R
b10 E
b10 S
b10 W
b101 I
b101 N
13
b101 H
b101 M
b101 [
b101 \
b11 =
1.
b0 /
b0 8
b0 C
b0 Q
11
b101 J
b101 X
b101 Z
b0 4
b0 ;
b0 @
b0 O
b1 2
b1 :
b1 A
b1 P
b100 7
b100 <
b100 ?
b100 U
b10 >
1#
#190
0#
#195
b1 K
b1 R
b1 I
b1 N
b1 H
b1 M
b1 [
b1 \
b10 =
b1 /
b1 8
b1 C
b1 Q
b10 F
b10 T
b10 V
01
b0 E
b0 S
b0 W
b1 J
b1 X
b1 Z
b1 4
b1 ;
b1 @
b1 O
b0 2
b0 :
b0 A
b0 P
b111 7
b111 <
b111 ?
b111 U
b11 >
1#
#200
0#
#205
b110 K
b110 R
b1 E
b1 S
b1 W
b110 I
b110 N
13
b110 H
b110 M
b110 [
b110 \
b11 =
1.
b0 /
b0 8
b0 C
b0 Q
11
b110 J
b110 X
b110 Z
b101 F
b101 T
b101 V
b0 4
b0 ;
b0 @
b0 O
b1 2
b1 :
b1 A
b1 P
b100 7
b100 <
b100 ?
b100 U
b10 >
1#
#210
0#
#215
1-
b0 K
b0 R
b0 I
b0 N
b0 H
b0 M
b0 [
b0 \
b100 =
b1 /
b1 8
b1 C
b1 Q
b1 F
b1 T
b1 V
01
b0 E
b0 S
b0 W
b0 J
b0 X
b0 Z
b1 4
b1 ;
b1 @
b1 O
b0 2
b0 :
b0 A
b0 P
b111 7
b111 <
b111 ?
b111 U
b11 >
1#
#220
0#
#225
b110 K
b110 R
0-
b110 I
b110 N
b110 H
b110 M
b110 [
b110 \
0.
b0 /
b0 8
b0 C
b0 Q
b110 J
b110 X
b110 Z
b110 !
b110 ,
b110 G
b110 ]
b110 F
b110 T
b110 V
b0 4
b0 ;
b0 @
b0 O
b0 7
b0 <
b0 ?
b0 U
1"
15
b100 >
1#
#230
b0 =
0#
1&
b1010000 '
#235
b0 K
b0 R
1-
b0 I
b0 N
1.
b110 F
b110 T
b110 V
b110 E
b110 S
b110 W
b0 H
b0 M
b0 [
b0 \
b0 J
b0 X
b0 Z
b1 =
13
11
b101 7
b101 <
b101 ?
b101 U
bz !
bz ,
bz G
bz ]
0"
05
b0 >
1#
#240
0#
r10 )
b100 $
b100 +
b100 D
b100 L
0&
b11110000 %
b100 *
#245
03
b100 K
b100 R
b10 =
0-
b100 I
b100 N
b1 /
b1 8
b1 C
b1 Q
01
b0 7
b0 <
b0 ?
b0 U
b0 F
b0 T
b0 V
b0 E
b0 S
b0 W
16
b1 >
1#
#250
0#
#255
b100 H
b100 M
b100 [
b100 \
b100 J
b100 X
b100 Z
13
b100 E
b100 S
b100 W
b100 K
b100 R
b100 7
b100 <
b100 ?
b100 U
b11 =
0-
b100 I
b100 N
b0 /
b0 8
b0 C
b0 Q
11
06
b1 2
b1 :
b1 A
b1 P
b10 >
1#
#260
0#
#265
b11 K
b11 R
b0 E
b0 S
b0 W
b11 I
b11 N
b11 H
b11 M
b11 [
b11 \
b10 =
b1 /
b1 8
b1 C
b1 Q
01
b11 J
b11 X
b11 Z
b100 F
b100 T
b100 V
b1 4
b1 ;
b1 @
b1 O
b0 2
b0 :
b0 A
b0 P
b111 7
b111 <
b111 ?
b111 U
b11 >
1#
#270
0#
#275
b100 F
b100 T
b100 V
b111 K
b111 R
b11 E
b11 S
b11 W
b111 I
b111 N
13
b111 H
b111 M
b111 [
b111 \
b11 =
1.
b0 /
b0 8
b0 C
b0 Q
11
b111 J
b111 X
b111 Z
b0 4
b0 ;
b0 @
b0 O
b1 2
b1 :
b1 A
b1 P
b100 7
b100 <
b100 ?
b100 U
b10 >
1#
#280
0#
#285
b10 K
b10 R
b10 I
b10 N
b10 H
b10 M
b10 [
b10 \
b10 =
b1 /
b1 8
b1 C
b1 Q
01
b0 E
b0 S
b0 W
b10 J
b10 X
b10 Z
b11 F
b11 T
b11 V
b1 4
b1 ;
b1 @
b1 O
b0 2
b0 :
b0 A
b0 P
b111 7
b111 <
b111 ?
b111 U
b11 >
1#
#290
0#
#295
b1001 K
b1001 R
b10 E
b10 S
b10 W
b1001 I
b1001 N
13
b1001 H
b1001 M
b1001 [
b1001 \
b11 =
1.
b0 /
b0 8
b0 C
b0 Q
b111 F
b111 T
b111 V
11
b1001 J
b1001 X
b1001 Z
b0 4
b0 ;
b0 @
b0 O
b1 2
b1 :
b1 A
b1 P
b100 7
b100 <
b100 ?
b100 U
b10 >
1#
#300
0#
#305
b1 K
b1 R
b1 I
b1 N
b1 H
b1 M
b1 [
b1 \
b10 =
b1 /
b1 8
b1 C
b1 Q
01
b0 E
b0 S
b0 W
b1 J
b1 X
b1 Z
b10 F
b10 T
b10 V
b1 4
b1 ;
b1 @
b1 O
b0 2
b0 :
b0 A
b0 P
b111 7
b111 <
b111 ?
b111 U
b11 >
1#
#310
0#
#315
b1010 K
b1010 R
b1 E
b1 S
b1 W
b1010 I
b1010 N
13
b1010 H
b1010 M
b1010 [
b1010 \
b11 =
1.
b0 /
b0 8
b0 C
b0 Q
b1001 F
b1001 T
b1001 V
11
b1010 J
b1010 X
b1010 Z
b0 4
b0 ;
b0 @
b0 O
b1 2
b1 :
b1 A
b1 P
b100 7
b100 <
b100 ?
b100 U
b10 >
1#
#320
0#
#325
b0 K
b0 R
1-
b0 I
b0 N
b0 H
b0 M
b0 [
b0 \
b100 =
b1 /
b1 8
b1 C
b1 Q
01
b0 E
b0 S
b0 W
b0 J
b0 X
b0 Z
b1 F
b1 T
b1 V
b1 4
b1 ;
b1 @
b1 O
b0 2
b0 :
b0 A
b0 P
b111 7
b111 <
b111 ?
b111 U
b11 >
1#
#330
0#
#335
b1010 K
b1010 R
0-
b1010 I
b1010 N
b1010 H
b1010 M
b1010 [
b1010 \
0.
b0 /
b0 8
b0 C
b0 Q
b1010 F
b1010 T
b1010 V
b1010 J
b1010 X
b1010 Z
b1010 !
b1010 ,
b1010 G
b1010 ]
b0 4
b0 ;
b0 @
b0 O
b0 7
b0 <
b0 ?
b0 U
1"
15
b100 >
1#
#340
b0 =
0#
1&
b1100100 '
#345
b0 K
b0 R
1-
b0 I
b0 N
1.
b1010 F
b1010 T
b1010 V
b1010 E
b1010 S
b1010 W
b0 H
b0 M
b0 [
b0 \
b0 J
b0 X
b0 Z
b1 =
13
11
b101 7
b101 <
b101 ?
b101 U
bz !
bz ,
bz G
bz ]
0"
05
b0 >
1#
#350
0#
r15 )
b101 $
b101 +
b101 D
b101 L
0&
b101011110 %
b101 *
#355
03
b101 K
b101 R
b0 F
b0 T
b0 V
b0 E
b0 S
b0 W
b10 =
0-
b101 I
b101 N
b1 /
b1 8
b1 C
b1 Q
01
b0 7
b0 <
b0 ?
b0 U
16
b1 >
1#
#360
0#
#365
b101 H
b101 M
b101 [
b101 \
b101 J
b101 X
b101 Z
13
b101 E
b101 S
b101 W
b101 K
b101 R
b100 7
b100 <
b100 ?
b100 U
b11 =
0-
b101 I
b101 N
b0 /
b0 8
b0 C
b0 Q
11
06
b1 2
b1 :
b1 A
b1 P
b10 >
1#
#370
0#
