older/verilog_code/cpe300/lab6_code/sum_sectioned/heads.v
/*
    resources for components and modules
        general data path (5 components)
        control unit (top-level)
*/

`ifndef H_heads
`define H_heads

`timescale 1ns/1ns      // change as needed
`define HALF 5          // half a clock period
`define T_ERROR 1       // wrap up skew, prop, fan in, or delay for debugging
`define SEED 999        // gauruntee $random sequence

// testing displays:
// "    ---> Valid"
// "    ---> !!!~~~*** FAIL ***~~~!!!"

// comment OFF, uncomment ON
`define DEBUG_TB -999          // allow test bench to print
`define DEBUG_WAVE -888        // testbench generates wave file

//`define DEBUG_CU -777          // control unit module prints
`define DEBUG_DP -666          // data path module prints

//`define DEBUG_MUX -111         // mux module prints, component 1 of 5
//`define DEBUG_RF -222          // register file module prints, component 2 of 5
//`define DEBUG_ALU -333         // alu module prints, component 3 of 5
//`define DEBUG_SH -444          // shifter module prints, component 4 of 5
//`define DEBUG_BUF -555         // buffer module prints, component 5 of 5


`endif 


////////~~~~~~~~END>  heads.v

older/verilog_code/cpe300/lab6_code/sum_sectioned/c3_alu/c3_alu.v
/*
    the alu
*/

`include "../heads.v"


module c3_alu (
                output reg [7:0] from_alu,
                input wire [7:0] A_bus,
                input wire [7:0] B_bus,
                input wire [2:0] ALU
            );

    parameter pass_A = 3'b000;     // bus A passes through
    parameter A_and_B = 3'b001;    // bitwise AND
    parameter A_or_B = 3'b010;     // bitwise OR
    parameter not_A = 3'b011;      // negate bus A
    parameter A_add_B = 3'b100;    // addition
    parameter A_sub_B = 3'b101;    // subtraction
    parameter inc_A = 3'b110;      // increment bus A
    parameter dec_A = 3'b111;      // decrement bus A

    always @ (*) begin 
        case(ALU) 
            pass_A  : from_alu = A_bus;                  
            A_and_B : from_alu = A_bus & B_bus;                  
            A_or_B  : from_alu = A_bus | B_bus; 
            not_A   : from_alu = ~A_bus;
            A_add_B : from_alu = A_bus + B_bus;
            A_sub_B : from_alu = A_bus - B_bus;
            inc_A   : from_alu = A_bus + 1'b1;
            dec_A   : from_alu = A_bus - 1'b1;                
        endcase

        `ifdef DEBUG_ALU
            $write("\n ************************************\n");
            $write(" {c3_alu}\n");
            $write("              ALU:  %3b\n", ALU);
            $write("           port_A:  %4b_%4b\n", A_bus[7:4], A_bus[3:0]);
            $write("           port_B:  %4b_%4b\n", B_bus[7:4], B_bus[3:0]);
            $write("              ---------------------\n");
            $write("       to_shifter:  %4b_%4b\n", 
                from_alu[7:4], from_alu[3:0]);
            $write(" ************************************\n");
        `endif
    end
endmodule


////////~~~~~~~~END>  c3_alu.v

older/verilog_code/cpe300/lab6_code/sum_sectioned/c3_alu/tb.v
/*
    test:  c3_alu
*/

`include "c3_alu.v"


module tb();
    wire [7:0] from_alu;
    reg [7:0] A_bus;
    reg [7:0] B_bus;
    reg [2:0] ALU;

    integer seed;
    integer ii;
    integer jj;

    c3_alu DUT (
                    .from_alu(from_alu),
                    .A_bus(A_bus),
                    .B_bus(B_bus),
                    .ALU(ALU)
                );
    
    initial begin
        `ifdef DEBUG_WAVE
            $dumpfile("wave.vcd");
            $dumpvars(0, tb);
        `endif
        seed = `SEED;
        $write("\n test component 3 of 5, the ALU\n\n");

        for (ii = 0; ii < 8; ii = ii + 1) begin
            ALU = ii;
            for (jj = 0; jj < 8; jj = jj + 1) begin
                A_bus[jj] = $random(seed) % 2;
                B_bus[jj] = $random(seed) % 2;
            end
            #`HALF;

            `ifdef DEBUG_TB
                $write(" operation =  %3b  ,  ", ALU);
                case(ALU)
                    3'b000 : $write("pass through\n");
                    3'b001 : $write("AND\n");
                    3'b010 : $write("OR\n");
                    3'b011 : $write("NOT\n");
                    3'b100 : $write("addition\n");
                    3'b101 : $write("subtraction\n");
                    3'b110 : $write("increment\n");
                    3'b111 : $write("decrement\n");
                endcase
                $write("         A =  %4b_%4b   \"%3d\"\n", 
                    A_bus[7:4], A_bus[3:0], A_bus);
                $write("         B =  %4b_%4b   \"%3d\"\n", 
                    B_bus[7:4], B_bus[3:0], B_bus);
                $write("      --------------------------\n");
                $write("  from_alu =  %4b_%4b   \"%3d\"\n\n", 
                    from_alu[7:4], from_alu[3:0], from_alu);
            `endif
        end

        #`HALF
        $write("\n\n\t\t ~ ~ ~ TEST COMPLETE ~ ~ ~\n\n");
        $finish;
    end

endmodule


////////~~~~~~~~END>  tb.v

older/verilog_code/cpe300/lab6_code/sum_sectioned/c3_alu/wave.vcd
$date
	Wed Oct  6 10:10:23 2021
$end
$version
	Icarus Verilog
$end
$timescale
	1ns
$end
$scope module tb $end
$var wire 8 ! from_alu [7:0] $end
$var reg 3 " ALU [2:0] $end
$var reg 8 # A_bus [7:0] $end
$var reg 8 $ B_bus [7:0] $end
$var integer 32 % ii [31:0] $end
$var integer 32 & jj [31:0] $end
$var integer 32 ' seed [31:0] $end
$scope module DUT $end
$var wire 3 ( ALU [2:0] $end
$var wire 8 ) A_bus [7:0] $end
$var wire 8 * B_bus [7:0] $end
$var reg 8 + from_alu [7:0] $end
$upscope $end
$upscope $end
$enddefinitions $end
#0
$dumpvars
b110000 +
b101100 *
b110000 )
b0 (
b1101001100101011110101010111 '
b1000 &
b0 %
b101100 $
b110000 #
b0 "
b110000 !
$end
#5
b10000100 !
b10000100 +
b10010100 $
b10010100 *
b10000111 #
b10000111 )
b1000010110111001101001011000111 '
b1000 &
b1 "
b1 (
b1 %
#10
b11110011 !
b11110011 +
b1100001 $
b1100001 *
b11010010 #
b11010010 )
b100001000101010100010000110111 '
b1000 &
b10 "
b10 (
b10 %
#15
b1111000 !
b1111000 +
b10100001 $
b10100001 *
b10000111 #
b10000111 )
b10111101101100110001000110100111 '
b1000 &
b11 "
b11 (
b11 %
#20
b111011 !
b111011 +
b100001 #
b100001 )
b11010 $
b11010 *
b110100010011010011101100010111 '
b1000 &
b100 "
b100 (
b100 %
#25
b1110 !
b1110 +
b1110011 #
b1110011 )
b1100101 $
b1100101 *
b10110001110101100000010000111 '
b1000 &
b101 "
b101 (
b101 %
#30
b11111001 !
b11111001 +
b10101101 $
b10101101 *
b11111000 #
b11111000 )
b11011010100100101010000111110111 '
b1000 &
b110 "
b110 (
b110 %
#35
b11100110 !
b11100110 +
b10010 $
b10010 *
b11100111 #
b11100111 )
b1001110001010111101111101100111 '
b1000 &
b111 "
b111 (
b111 %
#40
b1000 %
