older/verilog_code/cpe300/lab6_code/sum_sectioned/heads.v
/*
    resources for components and modules
        general data path (5 components)
        control unit (top-level)
*/

`ifndef H_heads
`define H_heads

`timescale 1ns/1ns      // change as needed
`define HALF 5          // half a clock period
`define T_ERROR 1       // wrap up skew, prop, fan in, or delay for debugging
`define SEED 999        // gauruntee $random sequence

// testing displays:
// "    ---> Valid"
// "    ---> !!!~~~*** FAIL ***~~~!!!"

// comment OFF, uncomment ON
`define DEBUG_TB -999          // allow test bench to print
`define DEBUG_WAVE -888        // testbench generates wave file

//`define DEBUG_CU -777          // control unit module prints
`define DEBUG_DP -666          // data path module prints

//`define DEBUG_MUX -111         // mux module prints, component 1 of 5
//`define DEBUG_RF -222          // register file module prints, component 2 of 5
//`define DEBUG_ALU -333         // alu module prints, component 3 of 5
//`define DEBUG_SH -444          // shifter module prints, component 4 of 5
//`define DEBUG_BUF -555         // buffer module prints, component 5 of 5


`endif 


////////~~~~~~~~END>  heads.v

older/verilog_code/cpe300/lab6_code/sum_sectioned/c2_register_file/c2_register_file.v
/*
    the register file
*/

`include "../heads.v"


module c2_register_file(
                            output wire [7:0] port_A,     // value assigned to port A
                            output wire [7:0] port_B,     // value assigned to port B
                            input wire [7:0] from_mux,    // bus after MUX selection
                            input wire WE,                // write enable
                            input wire [1:0] WA,          // write address
                            input wire RAE,               // port A read enable
                            input wire [1:0] RAA,         // port A Read address 
                            input wire RBE,               // port B read enable
                            input wire [1:0] RBA,         // port B read address
                            input wire clock
                        ); 
	
    parameter BLANK = 8'b0000_0000;

    // x4 8-bit registers "4x8"
	reg [7:0] internal [3:0]; 

    // only write if WE is active
	always @ (posedge clock) begin
        if (WE == 1'b1) internal[WA] <= from_mux;
    end
     
    // reading to ports is done in combination, if enabled
    assign port_A = (RAE == 1'b1) ? internal[RAA] : BLANK; 
    assign port_B = (RBE == 1'b1) ? internal[RBA] : BLANK;

    `ifdef DEBUG_RF
        always @ (negedge clock) begin
            $write("\n *****************************************************\n");
            $write(" {c2_register_file}                               %3t ns\n", $time);
            $write("                       from_mux:  %4b_%4b\n", from_mux[7:4], from_mux[3:0]);
            $write("        WE:  %1b  ,   WA:  %2b\n", WE, WA);
            $write("       RAE:  %1b  ,  RAA:  %2b\n", RAE, RAA);
            $write("       RBE:  %1b  ,  RBA:  %2b\n", RBE, RBA);
            $write("       -----------------------------------------------\n");
            $write("               portA:  %4b_%4b\n", port_A[7:4], port_A[3:0]);
            $write("               portB:  %4b_%4b\n", port_B[7:4], port_B[3:0]);
            $write("\n reg[00]:  %4b_%4b\n", internal[2'b00][7:4], internal[2'b00][3:0]);
            $write(" reg[01]:  %4b_%4b\n",   internal[2'b01][7:4], internal[2'b01][3:0]);
            $write(" reg[10]:  %4b_%4b\n",   internal[2'b10][7:4], internal[2'b10][3:0]);
            $write(" reg[11]:  %4b_%4b\n",   internal[2'b11][7:4], internal[2'b11][3:0]);
            $write(" *****************************************************\n");
        end
    `endif
endmodule


////////~~~~~~~~END>  c2_register_file.v

older/verilog_code/cpe300/lab6_code/sum_sectioned/c2_register_file/tb.v
/*
    test:  c2_register_file
*/

`include "c2_register_file.v"


module tb();
    wire [7:0] port_A;
    wire [7:0] port_B;
    reg [7:0] from_mux;
    reg WE;
    reg [1:0] WA;
    reg RAE;
    reg [1:0] RAA;
    reg RBE;
    reg [1:0] RBA;
    reg clock;

    integer seed;
    integer ii;

    c2_register_file DUT (
                            .port_A(port_A),  
                            .port_B(port_B),     
                            .from_mux(from_mux),
                            .WE(WE), 
                            .WA(WA),         
                            .RAE(RAE),             
                            .RAA(RAA),        
                            .RBE(RBE),            
                            .RBA(RBA),  
                            .clock(clock)
                        ); 
    
    always begin
        #`HALF;
        clock = ~clock;
    end

    initial begin
        `ifdef DEBUG_WAVE
            $dumpfile("wave.vcd");
            $dumpvars(0, tb);
        `endif
        seed = `SEED;
        $write("\n test component 2 of 5, the register file\n\n");
        clock = 1'b0;
        WE = 1'b0;
        WA = 2'b00;
        RAE = 1'b0;
        RAA = 2'b0;
        RBE = 1'b0;
        RBA = 2'b0;
        from_mux = 8'b0000_0000;

        $write("\n fill all 4 registers with values, don't read to ports\n\n");
        WE = 1'b1;
        RAE = 1'b0;
        RBE = 1'b0;
        for (ii = 0; ii < 4; ii = ii + 1) begin
            #`T_ERROR
            rand_reg(from_mux);
            WA = ii;
            #(`HALF + `HALF);
        end
       
        $write("\n fill all 4 registers with values, then read address to <port A>\n");
        WE = 1'b1;
        RAE = 1'b1;
        RBE = 1'b0;
        for (ii = 0; ii < 4; ii = ii + 1) begin
            #`T_ERROR
            rand_reg(from_mux);
            RAA = ii;
            WA = ii;
            #(`HALF + `HALF);
        end

        $write("\n fill all 4 registers with values, then read address to <port B>\n");
        WE = 1'b1;
        RAE = 1'b0;
        RBE = 1'b1;
        for (ii = 0; ii < 4; ii = ii + 1) begin
            #`T_ERROR
            rand_reg(from_mux);
            RBA = ii;
            WA = ii;
            #(`HALF + `HALF);
        end

        $write("\n fill all 4 registers with values, then read address to <port B>\n");
        WE = 1'b1;
        RAE = 1'b1;
        RBE = 1'b1;
        for (ii = 0; ii < 4; ii = ii + 1) begin
            #`T_ERROR
            rand_reg(from_mux);
            RBA = ii;
            RAA = ii;
            WA = ii;
            #(`HALF + `HALF);
        end
        
        #`HALF
        $write("\n\n\t\t ~ ~ ~ TEST COMPLETE ~ ~ ~\n\n");
        $finish;
    end

    task automatic rand_reg;
        output reg [7:0] r_r;
        integer idx;
        begin
            for (idx = 0; idx < 8; idx = idx + 1) begin
                r_r[idx] = $random(seed) % 2;
            end
        end
    endtask

endmodule


////////~~~~~~~END>  tb.v

older/verilog_code/cpe300/lab6_code/sum_sectioned/c2_register_file/wave.vcd
$date
	Wed Oct  6 11:00:26 2021
$end
$version
	Icarus Verilog
$end
$timescale
	1ns
$end
$scope module tb $end
$var wire 8 ! port_B [7:0] $end
$var wire 8 " port_A [7:0] $end
$var reg 2 # RAA [1:0] $end
$var reg 1 $ RAE $end
$var reg 2 % RBA [1:0] $end
$var reg 1 & RBE $end
$var reg 2 ' WA [1:0] $end
$var reg 1 ( WE $end
$var reg 1 ) clock $end
$var reg 8 * from_mux [7:0] $end
$var integer 32 + ii [31:0] $end
$var integer 32 , seed [31:0] $end
$scope module DUT $end
$var wire 2 - RAA [1:0] $end
$var wire 1 $ RAE $end
$var wire 2 . RBA [1:0] $end
$var wire 1 & RBE $end
$var wire 2 / WA [1:0] $end
$var wire 1 ( WE $end
$var wire 1 ) clock $end
$var wire 8 0 from_mux [7:0] $end
$var wire 8 1 port_B [7:0] $end
$var wire 8 2 port_A [7:0] $end
$upscope $end
$scope task rand_reg $end
$upscope $end
$upscope $end
$enddefinitions $end
#0
$dumpvars
b0 2
b0 1
b0 0
b0 /
b0 .
b0 -
b1111100111 ,
b0 +
b0 *
0)
1(
b0 '
0&
b0 %
0$
b0 #
b0 "
b0 !
$end
#1
b10100000 *
b10100000 0
b111010110000100110010100011111 ,
#5
1)
#10
0)
#11
b1 +
#12
b1 '
b1 /
b1101 *
b1101 0
b1101001100101011110101010111 ,
#15
1)
#20
0)
#22
b10 +
#23
b10 '
b10 /
b110101 *
b110101 0
b111011001010011110110010001111 ,
#25
1)
#30
0)
#33
b11 +
#34
b11 '
b11 /
b11000010 *
b11000010 0
b1000010110111001101001011000111 ,
#35
1)
#40
0)
#44
b10100000 "
b10100000 2
1$
b0 +
#45
b110 "
b110 2
b0 '
b0 /
b110 *
b110 0
b10000010111000100111111111111 ,
1)
#50
0)
#55
1)
b1 +
#56
b1101 "
b1101 2
b1 '
b1 /
b1 #
b1 -
b1111001 *
b1111001 0
b100001000101010100010000110111 ,
#60
0)
#65
b1111001 "
b1111001 2
1)
#66
b10 +
#67
b110101 "
b110101 2
b10 '
b10 /
b10 #
b10 -
b10111 *
b10111 0
b10111010100001000111101101111 ,
#70
0)
#75
b10111 "
b10111 2
1)
#77
b11 +
#78
b11000010 "
b11000010 2
b11 '
b11 /
b11 #
b11 -
b11001000 *
b11001000 0
b10111101101100110001000110100111 ,
#80
0)
#85
b11001000 "
b11001000 2
1)
#88
b110 !
b110 1
b0 "
b0 2
1&
0$
b0 +
#89
b0 '
b0 /
b10001001 *
b10001001 0
b1111010101111011010101011011111 ,
#90
0)
#95
b10001001 !
b10001001 1
1)
#99
b1 +
#100
b1111001 !
b1111001 1
b1 '
b1 /
b1 %
b1 .
b110 *
b110 0
b110100010011010011101100010111 ,
0)
#105
b110 !
b110 1
1)
#110
0)
b10 +
#111
b10111 !
b10111 1
b10 '
b10 /
b10 %
b10 .
b100111 *
b100111 0
b10100011000110101010001001001111 ,
#115
b100111 !
b100111 1
1)
#120
0)
#121
b11 +
#122
b11001000 !
b11001000 1
b11 '
b11 /
b11 %
b11 .
b111101 *
b111101 0
b10110001110101100000010000111 ,
#125
b111101 !
b111101 1
1)
#130
0)
#132
b111101 "
b111101 2
1$
b0 +
#133
b10001001 "
b10001001 2
b10001001 !
b10001001 1
b0 '
b0 /
b0 #
b0 -
b0 %
b0 .
b11100010 *
b11100010 0
b10100110100111100111010110111111 ,
#135
b11100010 "
b11100010 2
b11100010 !
b11100010 1
1)
#140
0)
#143
b1 +
#144
b110 "
b110 2
b110 !
b110 1
b1 '
b1 /
b1 #
b1 -
b1 %
b1 .
b11011101 *
b11011101 0
b11011010100100101010000111110111 ,
#145
b11011101 "
b11011101 2
b11011101 !
b11011101 1
1)
#150
0)
#154
b10 +
#155
b11101 "
b11101 2
b11101 !
b11101 1
b10 '
b10 /
b10 #
b10 -
b10 %
b10 .
b11101 *
b11101 0
b10111001010000000010010100101111 ,
1)
#160
0)
#165
1)
b11 +
#166
b111101 "
b111101 2
b111101 !
b111101 1
b11 '
b11 /
b11 #
b11 -
b11 %
b11 .
b1010110 *
b1010110 0
b1001110001010111101111101100111 ,
#170
0)
#175
b1010110 "
b1010110 2
b1010110 !
b1010110 1
1)
#176
b100 +
